Workbook

Sheet Criteria_Manual
A1: Criterion | B1: Name | C1: Score 1 Rule | D1: Score 0 Rule
A2: Q1 | B2: Time-Bound Net-Zero Target | C2: 1 = explicit company net-zero target + target year | D2: 0 = generic/national ambition or no company target year
A3: Q2 | B3: Measurable Interim Emissions-Reduction Target | C3: 1 = quantitative interim emissions target + target year + baseline/reference | D3: 0 = qualitative/incomplete target
A4: Q3 | B4: SBTi-Validated Target | C4: 1 = official SBTi validation applies to observation year | D4: 0 = aligned/committed/planned/pending or no validation
A5: Q4 | B5: Quantitative Scope 1 and Scope 2 Disclosure | C5: 1 = numerical Scope 1 AND Scope 2 with unit/reporting period | D5: 0 = one scope only or insufficient quantitative disclosure
A6: Q5 | B6: Quantitative Scope 3 Disclosure | C6: 1 = numerical Scope 3 total/material category; financed emissions may qualify for banks | D6: 0 = discussion without quantitative disclosure
A7: Q6 | B7: Comparable Multi-Year Emissions Data | C7: 1 = at least 2 comparable years of relevant emissions data | D7: 0 = single year or materially non-comparable
A8: Q7 | B8: Transition Implementation & Resource Allocation | C8: 1 = concrete transition action linked to measurable financial/operational resources | D8: 0 = generic activity without resource/implementation evidence
A9: Q8 | B9: Board-Level Climate Oversight | C9: 1 = board or board-level committee explicitly oversees climate | D9: 0 = management-only or no explicit board responsibility
A10: Q9 | B10: Measurable Progress Against Targets | C10: 1 = quantitative actual performance compared with target/baseline/pathway/prior period | D10: 0 = no measurable target/progress comparison
A11: Q10 | B11: Independent External Assurance | C11: 1 = independent assurance covers relevant GHG/climate/sustainability data | D11: 0 = financial audit only or no relevant assurance

Sheet Official_Report_Sources
A1: Ticker | B1: Company | C1: Country | D1: Annual/One Report Hub | E1: Sustainability/Climate Hub | F1: 2022 | G1: 2023 | H1: 2024 | I1: 2025 | J1: Notes
A2: PTT | B2: PTT Public Company Limited | C2: Thailand | D2: https://investor.pttplc.com/en/downloads/yearly-reports | E2: https://www.pttplc.com/en/sustainability | F2: Download from official hub | G2: Download from official hub | H2: Download from official hub | I2: Download from official hub
A3: PTTEP | B3: PTT Exploration and Production Public Company Limited | C3: Thailand | D3: https://www.pttep.com/en/investor-relations/document/annual-reports | E3: https://sustainability.pttep.com/en/document/sustainability-reports | F3: Download from official hub | G3: Download from official hub | H3: Download from official hub | I3: Download from official hub
A4: GPSC | B4: Global Power Synergy Public Company Limited | C4: Thailand | D4: https://www.gpscgroup.com/en/investor-relations/downloads/one-reports | E4: https://www.gpscgroup.com/en/downloads/sd-report | F4: Download from official hub | G4: Download from official hub | H4: Download from official hub | I4: Download from official hub
A5: GULF | B5: Gulf Development / predecessor GULF | C5: Thailand | D5: https://sustainability.gulf.co.th/en/document/sustainability-reports | E5: https://sustainability.gulf.co.th/en/document/sustainability-reports/archive | F5: Download from official hub | G5: Download from official hub | H5: Download from official hub | I5: Download from official hub
A6: KBANK | B6: Kasikornbank Public Company Limited | C6: Thailand | D6: https://www.kasikornbank.com/en/ir/finaninforeports/pages/financial-reports.aspx | E6: https://www.kasikornbank.com/en/sustainable-development/Pages/goals.aspx | F6: Download from official hub | G6: Download from official hub | H6: Download from official hub | I6: Download from official hub
A7: SCBX | B7: SCB X Public Company Limited | C7: Thailand | D7: https://www.scbx.com/en/investor-relations/ | E7: https://www.scbx.com/th/sustainability/report-and-disclosures/ | F7: Download from official hub | G7: Download from official hub | H7: Download from official hub | I7: Download from official hub
A8: SCC | B8: The Siam Cement Public Company Limited (SCG) | C8: Thailand | D8: https://scc.listedcompany.com/ | E8: https://www.scgsustainability.com/en/ | F8: Download from official hub | G8: Download from official hub | H8: Download from official hub | I8: Download from official hub
A9: CPALL | B9: CP ALL Public Company Limited | C9: Thailand | D9: https://www.cpall.co.th/en/investor/news-publications/publication/annual-report/ | E9: https://www.cpall.co.th/sustain/sd-report/ | F9: Download from official hub | G9: Download from official hub | H9: Download from official hub | I9: Download from official hub
A10: CPN | B10: Central Pattana Public Company Limited | C10: Thailand | D10: https://investor.centralpattana.co.th/ | E10: https://sustainability.centralpattana.co.th/en/document/sustainability-reports | F10: Download from official hub | G10: Download from official hub | H10: Download from official hub | I10: Download from official hub
A11: ADVANC | B11: Advanced Info Service Public Company Limited (AIS) | C11: Thailand | D11: https://investor.ais.co.th/en/document/annual-reports | E11: https://sustainability.ais.co.th/ | F11: Download from official hub | G11: Download from official hub | H11: Download from official hub | I11: Download from official hub
A12: BCP | B12: Bangchak Corporation Public Company Limited | C12: Thailand | D12: https://investor.bangchak.co.th/en/document/annual-reports | E12: https://investor.bangchak.co.th/en/resource-center | F12: Download from official hub | G12: Download from official hub | H12: Download from official hub | I12: Download from official hub
A13: AOT | B13: Airports of Thailand Public Company Limited | C13: Thailand | D13: https://investor.airportthai.co.th/download.html | E13: https://corporatestrategy.airportthai.co.th/en/sd/sd-report/ | F13: Download from official hub | G13: Download from official hub | H13: Download from official hub | I13: Download from official hub
... A20: MAERSK | B20: A.P. Moller - Maersk A/S | C20: Denmark | D20: https://investor.maersk.com/financials/annual-reports | E20: https://www.maersk.com/sustainability/reports-and-resources | F20: Download from official hub | G20: Download from official hub | H20: Download from official hub | I20: Download from official hub
A21: HOLCIM | B21: Holcim Ltd | C21: Switzerland | D21: https://www.holcim.com/investors/publications | E21: https://www.holcim.com/sustainability/esg/esg-policies-documents-reports | F21: Download from official hub | G21: Download from official hub | H21: Download from official hub | I21: Download from official hub | J21: Official Holcim archive lists reports for 2022, 2023, 2024 and 2025. Use the Integrated Annual Report plus Climate/Sustainability materials for each year.

Sheet PDF_Download_Manifest
A1: Ticker | B1: Year | C1: Type | D1: Priority | E1: What to Download | F1: Official Hub | G1: Suggested Filename | H1: Downloaded? | I1: Checked? | J1: Notes
A2: PTT | B2: 2022 | C2: Annual / One Report | D2: CORE | E2: Annual Report / Form 56-1 One Report covering this observation year | F2: https://investor.pttplc.com/en/downloads/yearly-reports | G2: PTT_2022_Annual_OneReport.pdf | H2: No | I2: No
A3: PTT | B3: 2022 | C3: Sustainability / Climate | D3: CORE | E3: Sustainability / ESG / Climate report covering this observation year | F3: https://www.pttplc.com/en/sustainability | G3: PTT_2022_Sustainability_Climate.pdf | H3: No | I3: No
A4: PTT | B4: 2022 | C4: Assurance / Data / Transition Plan | D4: SUPPLEMENT | E4: Separate assurance, ESG data book, TCFD/IFRS S2 or transition plan if the main report does not contain the evidence | F4: https://www.pttplc.com/en/sustainability | G4: PTT_2022_Supplement.pdf | H4: No | I4: No | J4: Only download if separate/relevant
A5: PTT | B5: 2023 | C5: Annual / One Report | D5: CORE | E5: Annual Report / Form 56-1 One Report covering this observation year | F5: https://investor.pttplc.com/en/downloads/yearly-reports | G5: PTT_2023_Annual_OneReport.pdf | H5: No | I5: No
A6: PTT | B6: 2023 | C6: Sustainability / Climate | D6: CORE | E6: Sustainability / ESG / Climate report covering this observation year | F6: https://www.pttplc.com/en/sustainability | G6: PTT_2023_Sustainability_Climate.pdf | H6: No | I6: No
A7: PTT | B7: 2023 | C7: Assurance / Data / Transition Plan | D7: SUPPLEMENT | E7: Separate assurance, ESG data book, TCFD/IFRS S2 or transition plan if the main report does not contain the evidence | F7: https://www.pttplc.com/en/sustainability | G7: PTT_2023_Supplement.pdf | H7: No | I7: No | J7: Only download if separate/relevant
A8: PTT | B8: 2024 | C8: Annual / One Report | D8: CORE | E8: Annual Report / Form 56-1 One Report covering this observation year | F8: https://investor.pttplc.com/en/downloads/yearly-reports | G8: PTT_2024_Annual_OneReport.pdf | H8: No | I8: No
A9: PTT | B9: 2024 | C9: Sustainability / Climate | D9: CORE | E9: Sustainability / ESG / Climate report covering this observation year | F9: https://www.pttplc.com/en/sustainability | G9: PTT_2024_Sustainability_Climate.pdf | H9: No | I9: No
A10: PTT | B10: 2024 | C10: Assurance / Data / Transition Plan | D10: SUPPLEMENT | E10: Separate assurance, ESG data book, TCFD/IFRS S2 or transition plan if the main report does not contain the evidence | F10: https://www.pttplc.com/en/sustainability | G10: PTT_2024_Supplement.pdf | H10: No | I10: No | J10: Only download if separate/relevant
A11: PTT | B11: 2025 | C11: Annual / One Report | D11: CORE | E11: Annual Report / Form 56-1 One Report covering this observation year | F11: https://investor.pttplc.com/en/downloads/yearly-reports | G11: PTT_2025_Annual_OneReport.pdf | H11: No | I11: No
A12: PTT | B12: 2025 | C12: Sustainability / Climate | D12: CORE | E12: Sustainability / ESG / Climate report covering this observation year | F12: https://www.pttplc.com/en/sustainability | G12: PTT_2025_Sustainability_Climate.pdf | H12: No | I12: No
A13: PTT | B13: 2025 | C13: Assurance / Data / Transition Plan | D13: SUPPLEMENT | E13: Separate assurance, ESG data book, TCFD/IFRS S2 or transition plan if the main report does not contain the evidence | F13: https://www.pttplc.com/en/sustainability | G13: PTT_2025_Supplement.pdf | H13: No | I13: No | J13: Only download if separate/relevant
A14: PTTEP | B14: 2022 | C14: Annual / One Report | D14: CORE | E14: Annual Report / Form 56-1 One Report covering this observation year | F14: https://www.pttep.com/en/investor-relations/document/annual-reports | G14: PTTEP_2022_Annual_OneReport.pdf | H14: No | I14: No
A15: PTTEP | B15: 2022 | C15: Sustainability / Climate | D15: CORE | E15: Sustainability / ESG / Climate report covering this observation year | F15: https://sustainability.pttep.com/en/document/sustainability-reports | G15: PTTEP_2022_Sustainability_Climate.pdf | H15: No | I15: No
A16: PTTEP | B16: 2022 | C16: Assurance / Data / Transition Plan | D16: SUPPLEMENT | E16: Separate assurance, ESG data book, TCFD/IFRS S2 or transition plan if the main report does not contain the evidence | F16: https://sustainability.pttep.com/en/document/sustainability-reports | G16: PTTEP_2022_Supplement.pdf | H16: No | I16: No | J16: Only download if separate/relevant
A17: PTTEP | B17: 2023 | C17: Annual / One Report | D17: CORE | E17: Annual Report / Form 56-1 One Report covering this observation year | F17: https://www.pttep.com/en/investor-relations/document/annual-reports | G17: PTTEP_2023_Annual_OneReport.pdf | H17: No | I17: No
A18: PTTEP | B18: 2023 | C18: Sustainability / Climate | D18: CORE | E18: Sustainability / ESG / Climate report covering this observation year | F18: https://sustainability.pttep.com/en/document/sustainability-reports | G18: PTTEP_2023_Sustainability_Climate.pdf | H18: No | I18: No
A19: PTTEP | B19: 2023 | C19: Assurance / Data / Transition Plan | D19: SUPPLEMENT | E19: Separate assurance, ESG data book, TCFD/IFRS S2 or transition plan if the main report does not contain the evidence | F19: https://sustainability.pttep.com/en/document/sustainability-reports | G19: PTTEP_2023_Supplement.pdf | H19: No | I19: No | J19: Only download if separate/relevant
A20: PTTEP | B20: 2024 | C20: Annual / One Report | D20: CORE | E20: Annual Report / Form 56-1 One Report covering this observation year | F20: https://www.pttep.com/en/investor-relations/document/annual-reports | G20: PTTEP_2024_Annual_OneReport.pdf | H20: No | I20: No
A21: PTTEP | B21: 2024 | C21: Sustainability / Climate | D21: CORE | E21: Sustainability / ESG / Climate report covering this observation year | F21: https://sustainability.pttep.com/en/document/sustainability-reports | G21: PTTEP_2024_Sustainability_Climate.pdf | H21: No | I21: No
A22: PTTEP | B22: 2024 | C22: Assurance / Data / Transition Plan | D22: SUPPLEMENT | E22: Separate assurance, ESG data book, TCFD/IFRS S2 or transition plan if the main report does not contain the evidence | F22: https://sustainability.pttep.com/en/document/sustainability-reports | G22: PTTEP_2024_Supplement.pdf | H22: No | I22: No | J22: Only download if separate/relevant
A23: PTTEP | B23: 2025 | C23: Annual / One Report | D23: CORE | E23: Annual Report / Form 56-1 One Report covering this observation year | F23: https://www.pttep.com/en/investor-relations/document/annual-reports | G23: PTTEP_2025_Annual_OneReport.pdf | H23: No | I23: No
A24: PTTEP | B24: 2025 | C24: Sustainability / Climate | D24: CORE | E24: Sustainability / ESG / Climate report covering this observation year | F24: https://sustainability.pttep.com/en/document/sustainability-reports | G24: PTTEP_2025_Sustainability_Climate.pdf | H24: No | I24: No
A25: PTTEP | B25: 2025 | C25: Assurance / Data / Transition Plan | D25: SUPPLEMENT | E25: Separate assurance, ESG data book, TCFD/IFRS S2 or transition plan if the main report does not contain the evidence | F25: https://sustainability.pttep.com/en/document/sustainability-reports | G25: PTTEP_2025_Supplement.pdf | H25: No | I25: No | J25: Only download if separate/relevant
A26: GPSC | B26: 2022 | C26: Annual / One Report | D26: CORE | E26: Annual Report / Form 56-1 One Report covering this observation year | F26: https://www.gpscgroup.com/en/investor-relations/downloads/one-reports | G26: GPSC_2022_Annual_OneReport.pdf | H26: No | I26: No
A27: GPSC | B27: 2022 | C27: Sustainability / Climate | D27: CORE | E27: Sustainability / ESG / Climate report covering this observation year | F27: https://www.gpscgroup.com/en/downloads/sd-report | G27: GPSC_2022_Sustainability_Climate.pdf | H27: No | I27: No
A28: GPSC | B28: 2022 | C28: Assurance / Data / Transition Plan | D28: SUPPLEMENT | E28: Separate assurance, ESG data book, TCFD/IFRS S2 or transition plan if the main report does not contain the evidence | F28: https://www.gpscgroup.com/en/downloads/sd-report | G28: GPSC_2022_Supplement.pdf | H28: No | I28: No | J28: Only download if separate/relevant
A29: GPSC | B29: 2023 | C29: Annual / One Report | D29: CORE | E29: Annual Report / Form 56-1 One Report covering this observation year | F29: https://www.gpscgroup.com/en/investor-relations/downloads/one-reports | G29: GPSC_2023_Annual_OneReport.pdf | H29: No | I29: No
A30: GPSC | B30: 2023 | C30: Sustainability / Climate | D30: CORE | E30: Sustainability / ESG / Climate report covering this observation year | F30: https://www.gpscgroup.com/en/downloads/sd-report | G30: GPSC_2023_Sustainability_Climate.pdf | H30: No | I30: No
A31: GPSC | B31: 2023 | C31: Assurance / Data / Transition Plan | D31: SUPPLEMENT | E31: Separate assurance, ESG data book, TCFD/IFRS S2 or transition plan if the main report does not contain the evidence | F31: https://www.gpscgroup.com/en/downloads/sd-report | G31: GPSC_2023_Supplement.pdf | H31: No | I31: No | J31: Only download if separate/relevant
A32: GPSC | B32: 2024 | C32: Annual / One Report | D32: CORE | E32: Annual Report / Form 56-1 One Report covering this observation year | F32: https://www.gpscgroup.com/en/investor-relations/downloads/one-reports | G32: GPSC_2024_Annual_OneReport.pdf | H32: No | I32: No
A33: GPSC | B33: 2024 | C33: Sustainability / Climate | D33: CORE | E33: Sustainability / ESG / Climate report covering this observation year | F33: https://www.gpscgroup.com/en/downloads/sd-report | G33: GPSC_2024_Sustainability_Climate.pdf | H33: No | I33: No
A34: GPSC | B34: 2024 | C34: Assurance / Data / Transition Plan | D34: SUPPLEMENT | E34: Separate assurance, ESG data book, TCFD/IFRS S2 or transition plan if the main report does not contain the evidence | F34: https://www.gpscgroup.com/en/downloads/sd-report | G34: GPSC_2024_Supplement.pdf | H34: No | I34: No | J34: Only download if separate/relevant
A35: GPSC | B35: 2025 | C35: Annual / One Report | D35: CORE | E35: Annual Report / Form 56-1 One Report covering this observation year | F35: https://www.gpscgroup.com/en/investor-relations/downloads/one-reports | G35: GPSC_2025_Annual_OneReport.pdf | H35: No | I35: No
A36: GPSC | B36: 2025 | C36: Sustainability / Climate | D36: CORE | E36: Sustainability / ESG / Climate report covering this observation year | F36: https://www.gpscgroup.com/en/downloads/sd-report | G36: GPSC_2025_Sustainability_Climate.pdf | H36: No | I36: No
A37: GPSC | B37: 2025 | C37: Assurance / Data / Transition Plan | D37: SUPPLEMENT | E37: Separate assurance, ESG data book, TCFD/IFRS S2 or transition plan if the main report does not contain the evidence | F37: https://www.gpscgroup.com/en/downloads/sd-report | G37: GPSC_2025_Supplement.pdf | H37: No | I37: No | J37: Only download if separate/relevant
A38: GULF | B38: 2022 | C38: Annual / One Report | D38: CORE | E38: Annual Report / Form 56-1 One Report covering this observation year | F38: https://sustainability.gulf.co.th/en/document/sustainability-reports | G38: GULF_2022_Annual_OneReport.pdf | H38: No | I38: No
A39: GULF | B39: 2022 | C39: Sustainability / Climate | D39: CORE | E39: Sustainability / ESG / Climate report covering this observation year | F39: https://sustainability.gulf.co.th/en/document/sustainability-reports/archive | G39: GULF_2022_Sustainability_Climate.pdf | H39: No | I39: No
A40: GULF | B40: 2022 | C40: Assurance / Data / Transition Plan | D40: SUPPLEMENT | E40: Separate assurance, ESG data book, TCFD/IFRS S2 or transition plan if the main report does not contain the evidence | F40: https://sustainability.gulf.co.th/en/document/sustainability-reports/archive | G40: GULF_2022_Supplement.pdf | H40: No | I40: No | J40: Only download if separate/relevant
A41: GULF | B41: 2023 | C41: Annual / One Report | D41: CORE | E41: Annual Report / Form 56-1 One Report covering this observation year | F41: https://sustainability.gulf.co.th/en/document/sustainability-reports | G41: GULF_2023_Annual_OneReport.pdf | H41: No | I41: No
A42: GULF | B42: 2023 | C42: Sustainability / Climate | D42: CORE | E42: Sustainability / ESG / Climate report covering this observation year | F42: https://sustainability.gulf.co.th/en/document/sustainability-reports/archive | G42: GULF_2023_Sustainability_Climate.pdf | H42: No | I42: No
A43: GULF | B43: 2023 | C43: Assurance / Data / Transition Plan | D43: SUPPLEMENT | E43: Separate assurance, ESG data book, TCFD/IFRS S2 or transition plan if the main report does not contain the evidence | F43: https://sustainability.gulf.co.th/en/document/sustainability-reports/archive | G43: GULF_2023_Supplement.pdf | H43: No | I43: No | J43: Only download if separate/relevant
A44: GULF | B44: 2024 | C44: Annual / One Report | D44: CORE | E44: Annual Report / Form 56-1 One Report covering this observation year | F44: https://sustainability.gulf.co.th/en/document/sustainability-reports | G44: GULF_2024_Annual_OneReport.pdf | H44: No | I44: No
A45: GULF | B45: 2024 | C45: Sustainability / Climate | D45: CORE | E45: Sustainability / ESG / Climate report covering this observation year | F45: https://sustainability.gulf.co.th/en/document/sustainability-reports/archive | G45: GULF_2024_Sustainability_Climate.pdf | H45: No | I45: No
A46: GULF | B46: 2024 | C46: Assurance / Data / Transition Plan | D46: SUPPLEMENT | E46: Separate assurance, ESG data book, TCFD/IFRS S2 or transition plan if the main report does not contain the evidence | F46: https://sustainability.gulf.co.th/en/document/sustainability-reports/archive | G46: GULF_2024_Supplement.pdf | H46: No | I46: No | J46: Only download if separate/relevant
A47: GULF | B47: 2025 | C47: Annual / One Report | D47: CORE | E47: Annual Report / Form 56-1 One Report covering this observation year | F47: https://sustainability.gulf.co.th/en/document/sustainability-reports | G47: GULF_2025_Annual_OneReport.pdf | H47: No | I47: No
A48: GULF | B48: 2025 | C48: Sustainability / Climate | D48: CORE | E48: Sustainability / ESG / Climate report covering this observation year | F48: https://sustainability.gulf.co.th/en/document/sustainability-reports/archive | G48: GULF_2025_Sustainability_Climate.pdf | H48: No | I48: No
A49: GULF | B49: 2025 | C49: Assurance / Data / Transition Plan | D49: SUPPLEMENT | E49: Separate assurance, ESG data book, TCFD/IFRS S2 or transition plan if the main report does not contain the evidence | F49: https://sustainability.gulf.co.th/en/document/sustainability-reports/archive | G49: GULF_2025_Supplement.pdf | H49: No | I49: No | J49: Only download if separate/relevant
A50: KBANK | B50: 2022 | C50: Annual / One Report | D50: CORE | E50: Annual Report / Form 56-1 One Report covering this observation year | F50: https://www.kasikornbank.com/en/ir/finaninforeports/pages/financial-reports.aspx | G50: KBANK_2022_Annual_OneReport.pdf | H50: No | I50: No
A51: KBANK | B51: 2022 | C51: Sustainability / Climate | D51: CORE | E51: Sustainability / ESG / Climate report covering this observation year | F51: https://www.kasikornbank.com/en/sustainable-development/Pages/goals.aspx | G51: KBANK_2022_Sustainability_Climate.pdf | H51: No | I51: No
A52: KBANK | B52: 2022 | C52: Assurance / Data / Transition Plan | D52: SUPPLEMENT | E52: Separate assurance, ESG data book, TCFD/IFRS S2 or transition plan if the main report does not contain the evidence | F52: https://www.kasikornbank.com/en/sustainable-development/Pages/goals.aspx | G52: KBANK_2022_Supplement.pdf | H52: No | I52: No | J52: Only download if separate/relevant
A53: KBANK | B53: 2023 | C53: Annual / One Report | D53: CORE | E53: Annual Report / Form 56-1 One Report covering this observation year | F53: https://www.kasikornbank.com/en/ir/finaninforeports/pages/financial-reports.aspx | G53: KBANK_2023_Annual_OneReport.pdf | H53: No | I53: No
A54: KBANK | B54: 2023 | C54: Sustainability / Climate | D54: CORE | E54: Sustainability / ESG / Climate report covering this observation year | F54: https://www.kasikornbank.com/en/sustainable-development/Pages/goals.aspx | G54: KBANK_2023_Sustainability_Climate.pdf | H54: No | I54: No
A55: KBANK | B55: 2023 | C55: Assurance / Data / Transition Plan | D55: SUPPLEMENT | E55: Separate assurance, ESG data book, TCFD/IFRS S2 or transition plan if the main report does not contain the evidence | F55: https://www.kasikornbank.com/en/sustainable-development/Pages/goals.aspx | G55: KBANK_2023_Supplement.pdf | H55: No | I55: No | J55: Only download if separate/relevant
A56: KBANK | B56: 2024 | C56: Annual / One Report | D56: CORE | E56: Annual Report / Form 56-1 One Report covering this observation year | F56: https://www.kasikornbank.com/en/ir/finaninforeports/pages/financial-reports.aspx | G56: KBANK_2024_Annual_OneReport.pdf | H56: No | I56: No
A57: KBANK | B57: 2024 | C57: Sustainability / Climate | D57: CORE | E57: Sustainability / ESG / Climate report covering this observation year | F57: https://www.kasikornbank.com/en/sustainable-development/Pages/goals.aspx | G57: KBANK_2024_Sustainability_Climate.pdf | H57: No | I57: No
A58: KBANK | B58: 2024 | C58: Assurance / Data / Transition Plan | D58: SUPPLEMENT | E58: Separate assurance, ESG data book, TCFD/IFRS S2 or transition plan if the main report does not contain the evidence | F58: https://www.kasikornbank.com/en/sustainable-development/Pages/goals.aspx | G58: KBANK_2024_Supplement.pdf | H58: No | I58: No | J58: Only download if separate/relevant
A59: KBANK | B59: 2025 | C59: Annual / One Report | D59: CORE | E59: Annual Report / Form 56-1 One Report covering this observation year | F59: https://www.kasikornbank.com/en/ir/finaninforeports/pages/financial-reports.aspx | G59: KBANK_2025_Annual_OneReport.pdf | H59: No | I59: No
A60: KBANK | B60: 2025 | C60: Sustainability / Climate | D60: CORE | E60: Sustainability / ESG / Climate report covering this observation year | F60: https://www.kasikornbank.com/en/sustainable-development/Pages/goals.aspx | G60: KBANK_2025_Sustainability_Climate.pdf | H60: No | I60: No
A61: KBANK | B61: 2025 | C61: Assurance / Data / Transition Plan | D61: SUPPLEMENT | E61: Separate assurance, ESG data book, TCFD/IFRS S2 or transition plan if the main report does not contain the evidence | F61: https://www.kasikornbank.com/en/sustainable-development/Pages/goals.aspx | G61: KBANK_2025_Supplement.pdf | H61: No | I61: No | J61: Only download if separate/relevant
A62: SCBX | B62: 2022 | C62: Annual / One Report | D62: CORE | E62: Annual Report / Form 56-1 One Report covering this observation year | F62: https://www.scbx.com/en/investor-relations/ | G62: SCBX_2022_Annual_OneReport.pdf | H62: No | I62: No
A63: SCBX | B63: 2022 | C63: Sustainability / Climate | D63: CORE | E63: Sustainability / ESG / Climate report covering this observation year | F63: https://www.scbx.com/th/sustainability/report-and-disclosures/ | G63: SCBX_2022_Sustainability_Climate.pdf | H63: No | I63: No
A64: SCBX | B64: 2022 | C64: Assurance / Data / Transition Plan | D64: SUPPLEMENT | E64: Separate assurance, ESG data book, TCFD/IFRS S2 or transition plan if the main report does not contain the evidence | F64: https://www.scbx.com/th/sustainability/report-and-disclosures/ | G64: SCBX_2022_Supplement.pdf | H64: No | I64: No | J64: Only download if separate/relevant
A65: SCBX | B65: 2023 | C65: Annual / One Report | D65: CORE | E65: Annual Report / Form 56-1 One Report covering this observation year | F65: https://www.scbx.com/en/investor-relations/ | G65: SCBX_2023_Annual_OneReport.pdf | H65: No | I65: No
A66: SCBX | B66: 2023 | C66: Sustainability / Climate | D66: CORE | E66: Sustainability / ESG / Climate report covering this observation year | F66: https://www.scbx.com/th/sustainability/report-and-disclosures/ | G66: SCBX_2023_Sustainability_Climate.pdf | H66: No | I66: No
A67: SCBX | B67: 2023 | C67: Assurance / Data / Transition Plan | D67: SUPPLEMENT | E67: Separate assurance, ESG data book, TCFD/IFRS S2 or transition plan if the main report does not contain the evidence | F67: https://www.scbx.com/th/sustainability/report-and-disclosures/ | G67: SCBX_2023_Supplement.pdf | H67: No | I67: No | J67: Only download if separate/relevant
A68: SCBX | B68: 2024 | C68: Annual / One Report | D68: CORE | E68: Annual Report / Form 56-1 One Report covering this observation year | F68: https://www.scbx.com/en/investor-relations/ | G68: SCBX_2024_Annual_OneReport.pdf | H68: No | I68: No
A69: SCBX | B69: 2024 | C69: Sustainability / Climate | D69: CORE | E69: Sustainability / ESG / Climate report covering this observation year | F69: https://www.scbx.com/th/sustainability/report-and-disclosures/ | G69: SCBX_2024_Sustainability_Climate.pdf | H69: No | I69: No
A70: SCBX | B70: 2024 | C70: Assurance / Data / Transition Plan | D70: SUPPLEMENT | E70: Separate assurance, ESG data book, TCFD/IFRS S2 or transition plan if the main report does not contain the evidence | F70: https://www.scbx.com/th/sustainability/report-and-disclosures/ | G70: SCBX_2024_Supplement.pdf | H70: No | I70: No | J70: Only download if separate/relevant
A71: SCBX | B71: 2025 | C71: Annual / One Report | D71: CORE | E71: Annual Report / Form 56-1 One Report covering this observation year | F71: https://www.scbx.com/en/investor-relations/ | G71: SCBX_2025_Annual_OneReport.pdf | H71: No | I71: No
A72: SCBX | B72: 2025 | C72: Sustainability / Climate | D72: CORE | E72: Sustainability / ESG / Climate report covering this observation year | F72: https://www.scbx.com/th/sustainability/report-and-disclosures/ | G72: SCBX_2025_Sustainability_Climate.pdf | H72: No | I72: No
A73: SCBX | B73: 2025 | C73: Assurance / Data / Transition Plan | D73: SUPPLEMENT | E73: Separate assurance, ESG data book, TCFD/IFRS S2 or transition plan if the main report does not contain the evidence | F73: https://www.scbx.com/th/sustainability/report-and-disclosures/ | G73: SCBX_2025_Supplement.pdf | H73: No | I73: No | J73: Only download if separate/relevant
A74: SCC | B74: 2022 | C74: Annual / One Report | D74: CORE | E74: Annual Report / Form 56-1 One Report covering this observation year | F74: https://scc.listedcompany.com/ | G74: SCC_2022_Annual_OneReport.pdf | H74: No | I74: No
A75: SCC | B75: 2022 | C75: Sustainability / Climate | D75: CORE | E75: Sustainability / ESG / Climate report covering this observation year | F75: https://www.scgsustainability.com/en/ | G75: SCC_2022_Sustainability_Climate.pdf | H75: No | I75: No
A76: SCC | B76: 2022 | C76: Assurance / Data / Transition Plan | D76: SUPPLEMENT | E76: Separate assurance, ESG data book, TCFD/IFRS S2 or transition plan if the main report does not contain the evidence | F76: https://www.scgsustainability.com/en/ | G76: SCC_2022_Supplement.pdf | H76: No | I76: No | J76: Only download if separate/relevant
A77: SCC | B77: 2023 | C77: Annual / One Report | D77: CORE | E77: Annual Report / Form 56-1 One Report covering this observation year | F77: https://scc.listedcompany.com/ | G77: SCC_2023_Annual_OneReport.pdf | H77: No | I77: No
A78: SCC | B78: 2023 | C78: Sustainability / Climate | D78: CORE | E78: Sustainability / ESG / Climate report covering this observation year | F78: https://www.scgsustainability.com/en/ | G78: SCC_2023_Sustainability_Climate.pdf | H78: No | I78: No
A79: SCC | B79: 2023 | C79: Assurance / Data / Transition Plan | D79: SUPPLEMENT | E79: Separate assurance, ESG data book, TCFD/IFRS S2 or transition plan if the main report does not contain the evidence | F79: https://www.scgsustainability.com/en/ | G79: SCC_2023_Supplement.pdf | H79: No | I79: No | J79: Only download if separate/relevant
A80: SCC | B80: 2024 | C80: Annual / One Report | D80: CORE | E80: Annual Report / Form 56-1 One Report covering this observation year | F80: https://scc.listedcompany.com/ | G80: SCC_2024_Annual_OneReport.pdf | H80: No | I80: No
A81: SCC | B81: 2024 | C81: Sustainability / Climate | D81: CORE | E81: Sustainability / ESG / Climate report covering this observation year | F81: https://www.scgsustainability.com/en/ | G81: SCC_2024_Sustainability_Climate.pdf | H81: No | I81: No
A82: SCC | B82: 2024 | C82: Assurance / Data / Transition Plan | D82: SUPPLEMENT | E82: Separate assurance, ESG data book, TCFD/IFRS S2 or transition plan if the main report does not contain the evidence | F82: https://www.scgsustainability.com/en/ | G82: SCC_2024_Supplement.pdf | H82: No | I82: No | J82: Only download if separate/relevant
A83: SCC | B83: 2025 | C83: Annual / One Report | D83: CORE | E83: Annual Report / Form 56-1 One Report covering this observation year | F83: https://scc.listedcompany.com/ | G83: SCC_2025_Annual_OneReport.pdf | H83: No | I83: No
A84: SCC | B84: 2025 | C84: Sustainability / Climate | D84: CORE | E84: Sustainability / ESG / Climate report covering this observation year | F84: https://www.scgsustainability.com/en/ | G84: SCC_2025_Sustainability_Climate.pdf | H84: No | I84: No
A85: SCC | B85: 2025 | C85: Assurance / Data / Transition Plan | D85: SUPPLEMENT | E85: Separate assurance, ESG data book, TCFD/IFRS S2 or transition plan if the main report does not contain the evidence | F85: https://www.scgsustainability.com/en/ | G85: SCC_2025_Supplement.pdf | H85: No | I85: No | J85: Only download if separate/relevant
A86: CPALL | B86: 2022 | C86: Annual / One Report | D86: CORE | E86: Annual Report / Form 56-1 One Report covering this observation year | F86: https://www.cpall.co.th/en/investor/news-publications/publication/annual-report/ | G86: CPALL_2022_Annual_OneReport.pdf | H86: No | I86: No
A87: CPALL | B87: 2022 | C87: Sustainability / Climate | D87: CORE | E87: Sustainability / ESG / Climate report covering this observation year | F87: https://www.cpall.co.th/sustain/sd-report/ | G87: CPALL_2022_Sustainability_Climate.pdf | H87: No | I87: No
A88: CPALL | B88: 2022 | C88: Assurance / Data / Transition Plan | D88: SUPPLEMENT | E88: Separate assurance, ESG data book, TCFD/IFRS S2 or transition plan if the main report does not contain the evidence | F88: https://www.cpall.co.th/sustain/sd-report/ | G88: CPALL_2022_Supplement.pdf | H88: No | I88: No | J88: Only download if separate/relevant
A89: CPALL | B89: 2023 | C89: Annual / One Report | D89: CORE | E89: Annual Report / Form 56-1 One Report covering this observation year | F89: https://www.cpall.co.th/en/investor/news-publications/publication/annual-report/ | G89: CPALL_2023_Annual_OneReport.pdf | H89: No | I89: No
A90: CPALL | B90: 2023 | C90: Sustainability / Climate | D90: CORE | E90: Sustainability / ESG / Climate report covering this observation year | F90: https://www.cpall.co.th/sustain/sd-report/ | G90: CPALL_2023_Sustainability_Climate.pdf | H90: No | I90: No
A91: CPALL | B91: 2023 | C91: Assurance / Data / Transition Plan | D91: SUPPLEMENT | E91: Separate assurance, ESG data book, TCFD/IFRS S2 or transition plan if the main report does not contain the evidence | F91: https://www.cpall.co.th/sustain/sd-report/ | G91: CPALL_2023_Supplement.pdf | H91: No | I91: No | J91: Only download if separate/relevant
A92: CPALL | B92: 2024 | C92: Annual / One Report | D92: CORE | E92: Annual Report / Form 56-1 One Report covering this observation year | F92: https://www.cpall.co.th/en/investor/news-publications/publication/annual-report/ | G92: CPALL_2024_Annual_OneReport.pdf | H92: No | I92: No
A93: CPALL | B93: 2024 | C93: Sustainability / Climate | D93: CORE | E93: Sustainability / ESG / Climate report covering this observation year | F93: https://www.cpall.co.th/sustain/sd-report/ | G93: CPALL_2024_Sustainability_Climate.pdf | H93: No | I93: No
A94: CPALL | B94: 2024 | C94: Assurance / Data / Transition Plan | D94: SUPPLEMENT | E94: Separate assurance, ESG data book, TCFD/IFRS S2 or transition plan if the main report does not contain the evidence | F94: https://www.cpall.co.th/sustain/sd-report/ | G94: CPALL_2024_Supplement.pdf | H94: No | I94: No | J94: Only download if separate/relevant
A95: CPALL | B95: 2025 | C95: Annual / One Report | D95: CORE | E95: Annual Report / Form 56-1 One Report covering this observation year | F95: https://www.cpall.co.th/en/investor/news-publications/publication/annual-report/ | G95: CPALL_2025_Annual_OneReport.pdf | H95: No | I95: No
A96: CPALL | B96: 2025 | C96: Sustainability / Climate | D96: CORE | E96: Sustainability / ESG / Climate report covering this observation year | F96: https://www.cpall.co.th/sustain/sd-report/ | G96: CPALL_2025_Sustainability_Climate.pdf | H96: No | I96: No
A97: CPALL | B97: 2025 | C97: Assurance / Data / Transition Plan | D97: SUPPLEMENT | E97: Separate assurance, ESG data book, TCFD/IFRS S2 or transition plan if the main report does not contain the evidence | F97: https://www.cpall.co.th/sustain/sd-report/ | G97: CPALL_2025_Supplement.pdf | H97: No | I97: No | J97: Only download if separate/relevant
A98: CPN | B98: 2022 | C98: Annual / One Report | D98: CORE | E98: Annual Report / Form 56-1 One Report covering this observation year | F98: https://investor.centralpattana.co.th/ | G98: CPN_2022_Annual_OneReport.pdf | H98: No | I98: No
A99: CPN | B99: 2022 | C99: Sustainability / Climate | D99: CORE | E99: Sustainability / ESG / Climate report covering this observation year | F99: https://sustainability.centralpattana.co.th/en/document/sustainability-reports | G99: CPN_2022_Sustainability_Climate.pdf | H99: No | I99: No
A100: CPN | B100: 2022 | C100: Assurance / Data / Transition Plan | D100: SUPPLEMENT | E100: Separate assurance, ESG data book, TCFD/IFRS S2 or transition plan if the main report does not contain the evidence | F100: https://sustainability.centralpattana.co.th/en/document/sustainability-reports | G100: CPN_2022_Supplement.pdf | H100: No | I100: No | J100: Only download if separate/relevant
...

Sheet Coding_800
A1: Type | B1: Company | C1: Year | D1: Sector | E1: Criterion | F1: Criterion Name | G1: Assistant Proposed Score | H1: Assistant Coding Status | I1: Evidence Summary / Quote | J1: Report | K1: Page | L1: Source URL | M1: Researcher Checked Evidence? | N1: Researcher Coder 1 Score | O1: Score Used (Provisional until checked) | P1: Rationale / Notes
A2: Thai Main Sample | B2: PTT | C2: 2022 | D2: Energy | E2: Q1 | F2: Time-Bound Net-Zero Target | G2: 1 | H2: AI evidence found — researcher verification required | I2: a Platinum class award. This reflects PTT’s commitment to conducting business with • Awarded Attachment sustainable social and environmental responsibility to achieve June 2022 the goals of carbon neutrality in 2040 and Net Zero Emissions • Awarded by in 2050 through the 3Ps strategy, namely Pursuit of Lower Thailand Institute of Emissions to drive PTT Group’s greenhouse gas emissions PTT received a plaque of honor Occupational Safety PTT Metro Forest Learning Center reduction projects; Portfolio Transformation, adjustment and Health received an honorary award for the Workation Thailand project, of investment plans to the future energy business (Public Organization) from the TGDA 2022. “Work From Everywhere” at Gold level. and bey | J2: PTT one report 2022(1).pdf | K2: p. 11 | L2: https://www.pttplc.com/en/sustainability | M2: No | O2: =IF(N2<>"",N2,G2) -> 1 | P2: Explicit time-bound company net-zero target found. | AI-assisted evidence retrieval; not yet personally verified by the researcher.
A3: Thai Main Sample | B3: PTT | C3: 2022 | D3: Energy | E3: Q2 | F3: Measurable Interim Emissions-Reduction Target | G3: 0 | H3: AI preliminary 0/uncertain — researcher verification required | I3: ement of Revenue Net Income Financial Position Financial Ratios Vision, Mission and PTT Values PTT Information THB 3,367,203 THB 91,175 THB 3,415,632 million million million Financial Highlights Milestone Achievement +40% +49% +187% -16% +21% +11% Net Profit to Total Sales Revenue Awards and Recognition 3.63 (%) Message from the Board of Directors 3,367,203 108,363 1% 13% 3,415,632 Economic, Petroleum 3% Return on Equity 1,040,862 688,345 26% and Petrochemical Review and Outlook 3,071,384 (%) 91,175 8.85 3% 855,254 648,619 21% 22% Section 1 Business Operations and Performance 2,544,183 1,193,594 Return on 2,258,818 Total Assets 720,931 462,835 14% Section 2 949,825 1% 1% (%) 3.76 875,440 2% 1% Corporate Governance 30% 8% 8% 779,25 | J3: PTT one report 2022(1).pdf | K3: p. 6 | L3: https://www.pttplc.com/en/sustainability | M3: No | O3: =IF(N3<>"",N3,G3) -> 0 | P3: Quantitative target wording did not clearly contain all three required elements: magnitude, target year and baseline/reference point. | AI-assisted evidence retrieval; not yet personally verified by the researcher.
A4: Thai Main Sample | B4: PTT | C4: 2022 | D4: Energy | E4: Q3 | F4: SBTi-Validated Target | G4: 0 | H4: AI preliminary 0/uncertain — researcher verification required | I4: No explicit SBTi validation statement found in the selected reports. | J4: PTT one report 2022(1).pdf | L4: https://www.pttplc.com/en/sustainability | M4: No | O4: =IF(N4<>"",N4,G4) -> 0 | P4: No official SBTi validation applicable to the observation year was evidenced; alignment, commitment, submission or later validation does not qualify. | AI-assisted evidence retrieval; not yet personally verified by the researcher.
A5: Thai Main Sample | B5: PTT | C5: 2022 | D5: Energy | E5: Q4 | F5: Quantitative Scope 1 and Scope 2 Disclosure | G5: 0 | H5: AI preliminary 0/uncertain — researcher verification required | I5: No qualifying evidence found in selected report(s). | J5: PTT one report 2022(1).pdf | L5: https://www.pttplc.com/en/sustainability | M5: No | O5: =IF(N5<>"",N5,G5) -> 0 | P5: No qualifying evidence found under the strict coding rule. | AI-assisted evidence retrieval; not yet personally verified by the researcher.
A6: Thai Main Sample | B6: PTT | C6: 2022 | D6: Energy | E6: Q5 | F6: Quantitative Scope 3 Disclosure | G6: 0 | H6: AI preliminary 0/uncertain — researcher verification required | I6: No qualifying evidence found in selected report(s). | J6: PTT one report 2022(1).pdf | L6: https://www.pttplc.com/en/sustainability | M6: No | O6: =IF(N6<>"",N6,G6) -> 0 | P6: No qualifying evidence found under the strict coding rule. | AI-assisted evidence retrieval; not yet personally verified by the researcher.
A7: Thai Main Sample | B7: PTT | C7: 2022 | D7: Energy | E7: Q6 | F7: Comparable Multi-Year Emissions Data | G7: 0 | H7: AI preliminary 0/uncertain — researcher verification required | I7: 020 56-1 One Report 2022 021 56-1 One Report 2022 PTT Public Company Limited Awards and Recognition PTT Public Company Limited Awards and Recognition PTT received the Outstanding 56-1 One Report 2022 Organization Award from PTT Public Company Limited King Prajadhipok’s Institute Association. Governance His Excellency Chuan Leekpai, President of the National Assembly, presented a plaque of honor “Outstanding Organization Association of King Prajadhipok’s Institute” Contents PTT received the State Excellence for 2022 to Mr. Auttapol Rer | J7: PTT one report 2022(1).pdf | K7: p. 12 | L7: https://www.pttplc.com/en/sustainability | M7: No | O7: =IF(N7<>"",N7,G7) -> 0 | P7: A multi-year emissions series was not sufficiently evidenced on the selected disclosure. | AI-assisted evidence retrieval; not yet personally verified by the researcher.
A8: Thai Main Sample | B8: PTT | C8: 2022 | D8: Energy | E8: Q7 | F8: Transition Implementation & Resource Allocation | G8: 0 | H8: AI conservative 0 — evidence snippet did not satisfy all strict rule elements; researcher recheck recommended | I8: as transmission, international trading, new business Thailand Securities Depository Company Limited Sales and Service Revenue 1,615,665 2,258,818 3,367,203 Milestone Achievement and infrastructure business; the rest are invested through 93, 14th Floor, The Stock Exchange of Thailand Building, Earnings before Interest, subsidiaries joint arrangements and associates, and Ratchadaphisek Road, Din Daeng, Din Daeng, Awards and Recognition Taxes, Depreciation and Amortization (EBITDA) 225,672 427,956 491,288 PTT Group, namely exploration and production, liquefied Bangkok 10400, Thailand Message from the Board of Directors natural gas, petrochemical and refining, oil and retail, Telephone: 66 (0) 2009-9999 Profit attribute to Equity Hold | J8: PTT one report 2022(1).pdf | K8: p. 5 | L8: https://www.pttplc.com/en/sustainability | M8: No | O8: =IF(N8<>"",N8,G8) -> 0 | P8: Automated retrieval found a potentially relevant page, but the captured evidence did not contain all strict coding elements together. Conservatively coded 0 pending researcher verification.
A9: Thai Main Sample | B9: PTT | C9: 2022 | D9: Energy | E9: Q8 | F9: Board-Level Climate Oversight | G9: 1 | H9: AI evidence found — researcher verification required | I9: on 2 Corporate Governance Attachment Financial Highlights Milestone Achievement 004 Vision, Mission and PTT Values 041 1. Structure and Business Operations 229 6. Corporate Governance 367 Attachment 1 Information of the Board of Directors, Awards and Recognition 006 PTT Information of PTT Group 258 7. Governance Structure Executives, Controlling Persons Message from the Board of Directors 007 Financial Highlights 122 2. Risk Management and Key Data on the Board of Directors, and Company Secretary Economic, Petroleum 010 Milestone Achievement 134 3. Driving Business towards Sustainability Specific Committees, Management, 442 Attachment 2 and Petrochemical Review and Outlook Details of Directors and Subsidiaries 016 Awards and Recog | J9: PTT one report 2022(1).pdf | K9: p. 3 | L9: https://www.pttplc.com/en/sustainability | M9: No | O9: =IF(N9<>"",N9,G9) -> 1 | P9: Board or board-level committee has explicit oversight/responsibility for climate or sustainability matters. | AI-assisted evidence retrieval; not yet personally verified by the researcher.
A10: Thai Main Sample | B10: PTT | C10: 2022 | D10: Energy | E10: Q9 | F10: Measurable Progress Against Targets | G10: 0 | H10: AI preliminary 0/uncertain — researcher verification required | I10: ement of Revenue Net Income Financial Position Financial Ratios Vision, Mission and PTT Values PTT Information THB 3,367,203 THB 91,175 THB 3,415,632 million million million Financial Highlights Milestone Achievement +40% +49% +187% -16% +21% +11% Net Profit to Total Sales Revenue Awards and Recognition 3.63 (%) Message from the Board of Directors 3,367,203 108,363 1% 13% 3,415,632 Economic, Petroleum 3% Return on Equity 1,040,862 688,345 26% and Petrochemical Review and Outlook 3,071,384 (%) 91,175 8.85 3% 855,254 648,619 21% 22% Section 1 Business Operations and Performance 2,544,183 1,193,594 Return on 2,258,818 Total Assets 720,931 462,835 14% Section 2 949,825 1% 1% (%) 3.76 875,440 2% 1% Corporate Governance 30% 8% 8% 779,25 | J10: PTT one report 2022(1).pdf | K10: p. 6 | L10: https://www.pttplc.com/en/sustainability | M10: No | O10: =IF(N10<>"",N10,G10) -> 0 | P10: Quantitative emissions are present but measurable progress against a target/baseline/pathway was not sufficiently evidenced. | AI-assisted evidence retrieval; not yet personally verified by the researcher.
A11: Thai Main Sample | B11: PTT | C11: 2022 | D11: Energy | E11: Q10 | F11: Independent External Assurance | G11: 0 | H11: AI preliminary 0/uncertain — researcher verification required | I11: oard and Duties and Responsibilities of Specific Committees of PTT Public Section Company Limited Attachment Financial Report 445 Attachment 6 Report of the Audit Committee 446 About This Report 366 Financial Report 447 Assurance Report | J11: PTT one report 2022(1).pdf | K11: p. 3 | L11: https://www.pttplc.com/en/sustainability | M11: No | O11: =IF(N11<>"",N11,G11) -> 0 | P11: External audit/assurance language was found, but coverage of relevant GHG/climate data was not sufficiently clear. | AI-assisted evidence retrieval; not yet personally verified by the researcher.
A12: Thai Main Sample | B12: PTT | C12: 2023 | D12: Energy | E12: Q1 | F12: Time-Bound Net-Zero Target | G12: 0 | H12: AI conservative 0 — evidence snippet did not satisfy all strict rule elements; researcher recheck recommended | I12: nd the entire transportation network of the country. and local communities to form “Thailand’s Leading Society and Communities receiving terminal to increase ethane import capacity, Network towards Carbon Neutrality and Net Zero Goals”. 9. Internal Control and Connected (2) 19% in Natural Gas Transmission Pipeline 3) Being a “low-carbon and sustainable organization” This is for driving the participation of various sectors in Transaction Maintaining an excellent corporate standing in Thai society Business Unit, including Bang Pakong - South Bangkok ready to drive Thailand towards Net Zero: PTT Group has reducing greenhouse gas emissions, as well as speeding by exercising environmental stewardship of internationally Power Plant and | J12: PTT one report 2023.pdf | K12: p. 123 | L12: https://www.pttplc.com/en/sustainability | M12: No | O12: =IF(N12<>"",N12,G12) -> 0 | P12: Automated retrieval found a potentially relevant page, but the captured evidence did not contain all strict coding elements together. Conservatively coded 0 pending researcher verification.
A13: Thai Main Sample | B13: PTT | C13: 2023 | D13: Energy | E13: Q2 | F13: Measurable Interim Emissions-Reduction Target | G13: 1 | H13: AI evidence found — researcher verification required | I13: etitiveness information Governance 8.1 growth, and drive Enhancement 8.2 PTT Information and the economy Performance forward Financial Highlights Excellence Increasing renewable energy production capacity - 15 gigawatts by 2030 4.9 gigawatts Achievement Highlights Limiting PTT and PTT Group’s direct and indirect PTT Group: ≤ 51.5 million tons PTT Group: 15% reduction PTT Group: The 5th strategy: 6.6 14.2 17 greenhouse gas emissions (Scope 1 and 2) domestically of carbon dioxide equivalent by 2030 compared to the 2020 41.59 million tons of Eco-friendly Page 158 Awards and Recognition Developing the and internationally PTT: ≤ 11.5 million tons emissions carbon dioxide Development 7.1 15.2 business towards a 7.2 of carbon dioxide equ | J13: PTT one report 2023.pdf | K13: p. 72 | L13: https://www.pttplc.com/en/sustainability | M13: No | O13: =IF(N13<>"",N13,G13) -> 1 | P13: Quantitative interim reduction target includes target year and baseline/reference point. | AI-assisted evidence retrieval; not yet personally verified by the researcher.
A14: Thai Main Sample | B14: PTT | C14: 2023 | D14: Energy | E14: Q3 | F14: SBTi-Validated Target | G14: 0 | H14: AI preliminary 0/uncertain — researcher verification required | I14: 1 One Report 2023 PTT Public Company Limited August December August 2, 2022: August 17, 2022: December 15, 2022: Contents PTT International Holdings Limited (PTTIH) (a wholly owned The Energy Regulatory Commission (ERC) approved the criteria December 14, 2022: PTT Board of Directors approved the five-year (Year 2023 - 2027) PTT Board of Directors approved the shareholding subsidiary of PTT) has entered into a Share Purchase of natural gas tariff for natural gas transportation licensees investment plan of PTT and its wholly owned subsidiaries in Vision, Mission and PTT Values restructuring of AI & Robotics business by assigning SMH Agreement of its entire investment, being 100% of through pipeline, which consist of two components; | J14: PTT one report 2023.pdf | K14: p. 30 | L14: https://www.pttplc.com/en/sustainability | M14: No | O14: =IF(N14<>"",N14,G14) -> 0 | P14: No official SBTi validation applicable to the observation year was evidenced; alignment, commitment, submission or later validation does not qualify. | AI-assisted evidence retrieval; not yet personally verified by the researcher.
A15: Thai Main Sample | B15: PTT | C15: 2023 | D15: Energy | E15: Q4 | F15: Quantitative Scope 1 and Scope 2 Disclosure | G15: 1 | H15: AI evidence found — researcher verification required | I15: rting systems for market-based Scope 2 greenhouse gas emissions compared greenhouse gas emissions, absorption, and storage data, to the previous year. This increase was attributed to the Direct greenhouse gas emissions (scope 1)2, 3 43.47 47.27 45.39 40.73 Contents covering direct emissions (Scope 1), emissions from energy increased electricity purchases to meet the growing demand Biogenic CO2 emissions N/A N/A 0.004 7 0.007 Scope use (Scope 2), and other indirect emissions (Scope 3). from the expanded operational scope. Meanwhile, the volume 1&2 Indirect greenhouse gas emissions (scope 2) (location-based) 1.01 1.12 0.65 0.86 Vision, Mission and PTT Values These systems have been continuously improved to align of direct Scope 1 gr | J15: PTT one report 2023.pdf | K15: p. 85 | L15: https://www.pttplc.com/en/sustainability | M15: No | O15: =IF(N15<>"",N15,G15) -> 1 | P15: Quantitative Scope 1 and Scope 2 emissions are disclosed with numerical data. | AI-assisted evidence retrieval; not yet personally verified by the researcher.
A16: Thai Main Sample | B16: PTT | C16: 2023 | D16: Energy | E16: Q5 | F16: Quantitative Scope 3 Disclosure | G16: 1 | H16: AI evidence found — researcher verification required | I16: tents covering direct emissions (Scope 1), emissions from energy increased electricity purchases to meet the growing demand Biogenic CO2 emissions N/A N/A 0.004 7 0.007 Scope use (Scope 2), and other indirect emissions (Scope 3). from the expanded operational scope. Meanwhile, the volume 1&2 Indirect greenhouse gas emissions (scope 2) (location-based) 1.01 1.12 0.65 0.86 Vision, Mission and PTT Values These systems have been continuously improved to align of direct Scope 1 greenhouse gas emissions decreased from with international standards by enhancing methodologies, the previous year due to primary factors such as reduced Indirect greenhouse gas emissions (scope 2) (market-based) 2, 3 1.69 1.46 0.86 0.87 PTT Information operatio | J16: PTT one report 2023.pdf | K16: p. 85 | L16: https://www.pttplc.com/en/sustainability | M16: No | O16: =IF(N16<>"",N16,G16) -> 1 | P16: Quantitative Scope 3 emissions (including financed emissions where relevant) are disclosed. | AI-assisted evidence retrieval; not yet personally verified by the researcher.
A17: Thai Main Sample | B17: PTT | C17: 2023 | D17: Energy | E17: Q6 | F17: Comparable Multi-Year Emissions Data | G17: 0 | H17: AI conservative 0 — evidence snippet did not satisfy all strict rule elements; researcher recheck recommended | I17: rting systems for market-based Scope 2 greenhouse gas emissions compared greenhouse gas emissions, absorption, and storage data, to the previous year. This increase was attributed to the Direct greenhouse gas emissions (scope 1)2, 3 43.47 47.27 45.39 40.73 Contents covering direct emissions (Scope 1), emissions from energy increased electricity purchases to meet the growing demand Biogenic CO2 emissions N/A N/A 0.004 7 0.007 Scope use (Scope 2), and other indirect emissions (Scope 3). from the expanded operational scope. Meanwhile, the volume 1&2 Indirect greenhouse gas emissions (scope 2) (location-based) 1.01 1.12 0.65 0.86 Vision, Mission and PTT Values These systems have been continuously improved to align of direct Scope 1 gr | J17: PTT one report 2023.pdf | K17: p. 85 | L17: https://www.pttplc.com/en/sustainability | M17: No | O17: =IF(N17<>"",N17,G17) -> 0 | P17: Automated retrieval found a potentially relevant page, but the captured evidence did not contain all strict coding elements together. Conservatively coded 0 pending researcher verification.
A18: Thai Main Sample | B18: PTT | C18: 2023 | D18: Energy | E18: Q7 | F18: Transition Implementation & Resource Allocation | G18: 0 | H18: AI conservative 0 — evidence snippet did not satisfy all strict rule elements; researcher recheck recommended | I18: t (CFP). million of unrealized gain on fair value of commodity contracts, THB 5,479 million of gain on derivatives, THB 4,614 million Contents of gain on disposal of assets, and THB 3,013 million of share of profit from investments in joint ventures and associates and Vision, Mission and PTT Values Liabilities the change in net operating assets resulted in the increase in cash flow of THB 46,247 million while there were income taxes paid of THB 83,201 million. PTT Information As of December 31, 2023, PTT Group had total liabilities of THB 1,835,486 million, decreased by THB 46,453 million or Financial Highlights 2.5% from December 31, 2022, mainly from the followings; Net cash used in investing activities was THB 161,245 million m | J18: PTT one report 2023.pdf | K18: p. 106 | L18: https://www.pttplc.com/en/sustainability | M18: No | O18: =IF(N18<>"",N18,G18) -> 0 | P18: Automated retrieval found a potentially relevant page, but the captured evidence did not contain all strict coding elements together. Conservatively coded 0 pending researcher verification.
... A45: Thai Main Sample | B45: PTTEP | C45: 2022 | D45: Energy | E45: Q4 | F45: Quantitative Scope 1 and Scope 2 Disclosure | G45: 1 | H45: AI evidence found — researcher verification required | I45: has set a target to reduce GHG emissions intensity from our and (2) Application of various technologies to reduce E&P activities under PTTEP’s operational control covering GHG emissions from the production process, for Scope 1 and Scope 2 emissions by at least 25% within 2030 example, recovery flare gas or excess gas went back (from the base year 2012). Throughout the past decade, into the production process for further utilization, PTTEP was committed to continually reducing greenhouse energy efficiency improvement, production efficiency gas emissions (GHG emissions) through the implementation improvement, reduction of methane leak, adoption of various projects in both domestic and international assets. of renewable energy in op | J45: PTTEP sustainability report 2022.pdf | K45: p. 17 | L45: https://sustainability.pttep.com/en/document/sustainability-reports | M45: No | O45: =IF(N45<>"",N45,G45) -> 1 | P45: Quantitative Scope 1 and Scope 2 emissions are disclosed with numerical data. | AI-assisted evidence retrieval; not yet personally verified by the researcher.
A46: Thai Main Sample | B46: PTTEP | C46: 2022 | D46: Energy | E46: Q5 | F46: Quantitative Scope 3 Disclosure | G46: 0 | H46: AI preliminary 0/uncertain — researcher verification required | I46: No qualifying evidence found in selected report(s). | J46: PTTEP one report 2022.pdf | L46: https://sustainability.pttep.com/en/document/sustainability-reports | M46: No | O46: =IF(N46<>"",N46,G46) -> 0 | P46: No qualifying evidence found under the strict coding rule. | AI-assisted evidence retrieval; not yet personally verified by the researcher.
A47: Thai Main Sample | B47: PTTEP | C47: 2022 | D47: Energy | E47: Q6 | F47: Comparable Multi-Year Emissions Data | G47: 0 | H47: AI preliminary 0/uncertain — researcher verification required | I47: ation and Production and Production Production and Public Production Production Public Public Public Company Company Public Company Limited Limited Limited Company Company Limited Limited 56-1 One Report / Annual Report 2022 tes Notes Notes thetoNotes toNotes toto 424 the the Consolidated to the the Consolidated Consolidated Consolidated Consolidated PTT and and and Separate Exploration and Separate and Separate and SeparateFinancial Separate Financial Production Financial Public Statements Statements Statements Statements Statements Financial Financial Company Limited theFor r For For year theFor the year the the yearnded nded year nded year 31 December 31 December December 31 31 ended ended ended December 31 December 20222022 20 | J47: PTTEP one report 2022.pdf | K47: p. 420 | L47: https://sustainability.pttep.com/en/document/sustainability-reports | M47: No | O47: =IF(N47<>"",N47,G47) -> 0 | P47: A multi-year emissions series was not sufficiently evidenced on the selected disclosure. | AI-assisted evidence retrieval; not yet personally verified by the researcher.
A48: Thai Main Sample | B48: PTTEP | C48: 2022 | D48: Energy | E48: Q7 | F48: Transition Implementation & Resource Allocation | G48: 0 | H48: AI conservative 0 — evidence snippet did not satisfy all strict rule elements; researcher recheck recommended | I48: Participation Interest: 60% Participation Interest: 100% Operator: Eni Operator: Chevron Operator: PTTEP Group 1 On August 31, 2022, PTTEP Group has entered into a Sale and Purchase Agreement (SPA) to sell PTTEP Brazil Investments in Oil and Gas Exploration and 7 On March 14, 2022, PTTEP International Limited (PTTEPI), a wholly-owned subsidiary of PTTEP Group and a partner in the project, has assumed the operatorship Production Limitada, which holds 25% interest in the Barreirinhas AP1 Project and 20% interest in the Brazil BM-ES-23 Project. The completion will be subject of Yadana Project and Moattama Gas Transportation Company (MGTC), with effect from July 20, 2022. to conditions as prescribed in the SPA. 8 The concession of Co | J48: PTTEP sustainability report 2022.pdf | K48: p. 23 | L48: https://sustainability.pttep.com/en/document/sustainability-reports | M48: No | O48: =IF(N48<>"",N48,G48) -> 0 | P48: Automated retrieval found a potentially relevant page, but the captured evidence did not contain all strict coding elements together. Conservatively coded 0 pending researcher verification.
A49: Thai Main Sample | B49: PTTEP | C49: 2022 | D49: Energy | E49: Q8 | F49: Board-Level Climate Oversight | G49: 0 | H49: AI conservative 0 — evidence snippet did not satisfy all strict rule elements; researcher recheck recommended | I49: Governance Structure and Key Data on the Board of Directors, Specific Committees, Management, Employees, and Others 199 Form 56-1 One Report Year 2022 In 2022, the Company invested in human capital development programs at the total amount of THB 243,814,938 and provided more than 292,512 training and development hours for our employees with an average of 57 training and development hours per person per annum. PTTEP has a policy for management in implementing an Individual Competency Development Plan (ICDP) for PTTEP Staff. To ensure standardization, PTTEP | J49: PTTEP one report 2022.pdf | K49: p. 195 | L49: https://sustainability.pttep.com/en/document/sustainability-reports | M49: No | O49: =IF(N49<>"",N49,G49) -> 0 | P49: Automated retrieval found a potentially relevant page, but the captured evidence did not contain all strict coding elements together. Conservatively coded 0 pending researcher verification.
A50: Thai Main Sample | B50: PTTEP | C50: 2022 | D50: Energy | E50: Q9 | F50: Measurable Progress Against Targets | G50: 0 | H50: AI preliminary 0/uncertain — researcher verification required | I50: Structure and Business Operations 63 PTTEP 100% 75% 51% 20% 15% 50% 100% 49% 25% 49% PTT SPSE Energy PTTEP PTTEPI PTTEPO PTTEPS Digital Complex EH GHBR 25% PTTEP 75% Services 25% PTTEP 75% TC 100% 100% 100% 50% 100% 53.9496% 25.001% 100% 80% 37.0842% 100% 100% 100% 100% 100% 100% 25% PTTEP 75% PTTEP B8/32 PTTEP PTTEP PTTEP PTTEP PTTEP PTTEP PTTEP CPOC SHL Orange PTTEPH ATL MGTC EP-Tech BC HK G7 25% Partners SV KV HV HL AG ED 75% PTTEP 100% 100% 100% NH PTTEP 100% YS PTTEP PGH 50% Natuna 2 25% 28.5% 35% MENA HKO B.V. 100% 100% 100% 100% 100% 100% 100% HV JOC HL | J50: PTTEP one report 2022.pdf | K50: p. 59 | L50: https://sustainability.pttep.com/en/document/sustainability-reports | M50: No | O50: =IF(N50<>"",N50,G50) -> 0 | P50: Quantitative emissions are present but measurable progress against a target/baseline/pathway was not sufficiently evidenced. | AI-assisted evidence retrieval; not yet personally verified by the researcher.
A51: Thai Main Sample | B51: PTTEP | C51: 2022 | D51: Energy | E51: Q10 | F51: Independent External Assurance | G51: 0 | H51: AI preliminary 0/uncertain — researcher verification required | I51: opriateness. 9) Perform other duties relating to PTTEP risk management as may be assigned by the Board. The Risk Management Committee consists of at least 3 directors, while ensuring that at least one of them must be an independent director. As of December 31, 2022, the Committee comprised 4 members, 4 of which were independent directors as follows: Mr. Pitipan Tepartimargorn Chairman and Independent Director Lieutenant General Nimit Suwannarat Member and Independent Director Mr. Veerathai Santiprabhob Member and Independent Director Mr. Bundhit Eua-arporn Member and Independent Director Mr. Atikom Terbsiri has resigned from the positions of Director and Member of the Risk Management Committee. His resignation is effective from 30 | J51: PTTEP one report 2022.pdf | K51: p. 187 | L51: https://sustainability.pttep.com/en/document/sustainability-reports | M51: No | O51: =IF(N51<>"",N51,G51) -> 0 | P51: External audit/assurance language was found, but coverage of relevant GHG/climate data was not sufficiently clear. | AI-assisted evidence retrieval; not yet personally verified by the researcher.
A52: Thai Main Sample | B52: PTTEP | C52: 2023 | D52: Energy | E52: Q1 | F52: Time-Bound Net-Zero Target | G52: 1 | H52: AI evidence found — researcher verification required | I52: Building a Sustainable Tomorrow 261 9. Building a Sustainable Tomorrow 9.1 Striving towards Net Zero In 2023, PTTEP was able to reduce GHG emissions by more than 0.9 million tonnes of CO 2 equivalent. PTTEP acknowledges the critical business challenges posed This accomplishment results in a cumulative GHG reduction by the energy transition and the impacts of global warming of more than 2.4 million tonnes of CO2 equivalent since and climate change. Consequently, in 2022, the Company 2020. This is equivalent to CO2 absorption by 2.5 million announced our commitment through EP Net Zero 2050 rai of trees per | J52: PTTEP one report 2023.pdf | K52: p. 251 | L52: https://sustainability.pttep.com/en/document/sustainability-reports | M52: No | O52: =IF(N52<>"",N52,G52) -> 1 | P52: Explicit time-bound company net-zero target found. | AI-assisted evidence retrieval; not yet personally verified by the researcher.
A53: Thai Main Sample | B53: PTTEP | C53: 2023 | D53: Energy | E53: Q2 | F53: Measurable Interim Emissions-Reduction Target | G53: 0 | H53: AI preliminary 0/uncertain — researcher verification required | I53: PTTEP 100% 75% 51% 20% 15% 50% 100% 49% 25% 49% PTT PTT Energy PTTEP PTTEPI PTTEPO Siam Digital SPSE Complex EH GHBR 25% PTTEP 75% Structure and Business Operations Services 25% PTTEP 75% TC 50% 100% 53.9496% 25.001% 100% 80% 37.0842% 100% 100% 100% 100% 100% 100% 100% 100% 25% PTTEP 75% B8/32 PTTEP PTTEP PTTEP PTTEP PTTEP PTTEP PTTEP HK CPOC SHL Orange Partners PTTEPH ATL MGTC KV HV HL AG EP-Tech BC ED 25% SV 75% PTTEP 25% 28.5% 35% 100% NH 100% 100% PTTEP HV JOC HL JOC GBRS MENA PTTEP PGH HKO 50% Natuna 2 B.V. 100% 100% 1 | J53: PTTEP one report 2023.pdf | K53: p. 63 | L53: https://sustainability.pttep.com/en/document/sustainability-reports | M53: No | O53: =IF(N53<>"",N53,G53) -> 0 | P53: Quantitative target wording did not clearly contain all three required elements: magnitude, target year and baseline/reference point. | AI-assisted evidence retrieval; not yet personally verified by the researcher.
A54: Thai Main Sample | B54: PTTEP | C54: 2023 | D54: Energy | E54: Q3 | F54: SBTi-Validated Target | G54: 0 | H54: AI preliminary 0/uncertain — researcher verification required | I54: zero greenhouse gas emissions • Establish guidelines for the assessment of impacts related to the energy sector business such as ISO and of greenhouse gas emissions for GHG Criteria for Science Based Targets initiative (SBTi). These could affect Investment Decision Guidelines, including Internal the enforcement of greenhouse gas emission reductions Carbon Price that is used to consider new investment between the year and the target year 2050 and also offset projects. This is a tool to help assess the economic greenhouse gas emissions with specific types of carbon impact of new projects in relation to the Company’s credits, all of which may affect the Company’s operations. greenhouse gas emissions targets. Mitigation plan: PTTEP fo | J54: PTTEP one report 2023.pdf | K54: p. 95 | L54: https://sustainability.pttep.com/en/document/sustainability-reports | M54: No | O54: =IF(N54<>"",N54,G54) -> 0 | P54: No official SBTi validation applicable to the observation year was evidenced; alignment, commitment, submission or later validation does not qualify. | AI-assisted evidence retrieval; not yet personally verified by the researcher.
A55: Thai Main Sample | B55: PTTEP | C55: 2023 | D55: Energy | E55: Q4 | F55: Quantitative Scope 1 and Scope 2 Disclosure | G55: 1 | H55: AI evidence found — researcher verification required | I55: tegy, aiming to reach Net Zero Greenhouse Gas (GHG) through E&P portfolio management and the deployment of Emissions by 2050. This goal covers both direct emissions diverse technologies to reduce GHG emissions from the (Scope 1) and indirect emissions (Scope 2) of the exploration production process. Notable initiatives include flare gas and production business under PTTEP’s operational control. recovery and utilization, energy efficiency improvement, PTTEP has also set interim targets to reduce GHG emissions production efficiency enhancement, mitigation of methane intensity by at least 30 percent within 2030 and 50 percent leaks, and integration of renewable energy in operations within 2040 (from base year 2020). as well as effici | J55: PTTEP one report 2023.pdf | K55: p. 251 | L55: https://sustainability.pttep.com/en/document/sustainability-reports | M55: No | O55: =IF(N55<>"",N55,G55) -> 1 | P55: Quantitative Scope 1 and Scope 2 emissions are disclosed with numerical data. | AI-assisted evidence retrieval; not yet personally verified by the researcher.
A56: Thai Main Sample | B56: PTTEP | C56: 2023 | D56: Energy | E56: Q5 | F56: Quantitative Scope 3 Disclosure | G56: 0 | H56: AI preliminary 0/uncertain — researcher verification required | I56: No qualifying evidence found in selected report(s). | J56: PTTEP one report 2023.pdf | L56: https://sustainability.pttep.com/en/document/sustainability-reports | M56: No | O56: =IF(N56<>"",N56,G56) -> 0 | P56: No qualifying evidence found under the strict coding rule. | AI-assisted evidence retrieval; not yet personally verified by the researcher.
A57: Thai Main Sample | B57: PTTEP | C57: 2023 | D57: Energy | E57: Q6 | F57: Comparable Multi-Year Emissions Data | G57: 0 | H57: AI preliminary 0/uncertain — researcher verification required | I57: ancial Highlights 9 Contents Financial Highlights Message from Chairman and CEO Financial Highlights Total Assets Total Liabilities Total Equity Total Revenues Profit for the Year Financial Highlights (USD Million) 2021 2022 2023 Environmental, Social, Governance Dividend per Share (THB) 5.00 9.25 9.50* Highlight Performance 30,000 Dividend Yield (%)** 4.24 5.24 6.35 Value Creation * Total dividend of 2023 at the rate of THB 9.50 per share includes the interim dividend at the rate of THB 4.25 per share and the second half-year dividend at 26,380 the rate of THB 5.25 per share. Payments of the interim dividend and the second half-year dividend will be proposed in 2024 General Shareholder’s Meeting Stakeholders’ Voices 25,000 25,168 | J57: PTTEP one report 2023.pdf | K57: p. 6 | L57: https://sustainability.pttep.com/en/document/sustainability-reports | M57: No | O57: =IF(N57<>"",N57,G57) -> 0 | P57: A multi-year emissions series was not sufficiently evidenced on the selected disclosure. | AI-assisted evidence retrieval; not yet personally verified by the researcher.
A58: Thai Main Sample | B58: PTTEP | C58: 2023 | D58: Energy | E58: Q7 | F58: Transition Implementation & Resource Allocation | G58: 0 | H58: AI conservative 0 — evidence snippet did not satisfy all strict rule elements; researcher recheck recommended | I58: uishment. 6 In February 2023, PTTEP Group, along with Petronas Carigali Sdn Bhd. (PCSB), INPEX Cash Maple Pty Ltd and TotalEnergies Exploration Australia Pty Ltd. PTTEP AAA • On February 23, 2023, the sale of the entire investment in PTTEP Brazil Investments in However, all partners in the project remain obliged to decommissioning as prescribed and Petroleum Sarawak Exploration & Production Sdn Bhd. (PSEP) was awarded holds 100 percent interests in the retention lease and the divestment was completed on Oil and Gas Exploration and Production Limitada (PTTEP BL) which holds 25 percent by laws. the exploration Block SK325, which is located offshore of Sarawak, Malaysia. December 22, 2023. interest in the Barreirinhas AP1 Project and | J58: PTTEP one report 2023.pdf | K58: p. 35 | L58: https://sustainability.pttep.com/en/document/sustainability-reports | M58: No | O58: =IF(N58<>"",N58,G58) -> 0 | P58: Automated retrieval found a potentially relevant page, but the captured evidence did not contain all strict coding elements together. Conservatively coded 0 pending researcher verification.
A59: Thai Main Sample | B59: PTTEP | C59: 2023 | D59: Energy | E59: Q8 | F59: Board-Level Climate Oversight | G59: 0 | H59: AI conservative 0 — evidence snippet did not satisfy all strict rule elements; researcher recheck recommended | I59: Governance Structure and Key Data on the Board of Directors, Sub-Committees, Management, Employees, and Others 189 Board and the management. The Secretary of the Board of • Overseeing and advising the Board to ensure that Directors is also the accountable person in reviewing the directors perform their roles in compliance with relevant agenda and minutes of the Board’s meetings prior to their applicable laws, rules, and regulations as well as submission to the Board and managing documentation the Company’s objectives, Articles of Association, of the Share | J59: PTTEP one report 2023.pdf | K59: p. 179 | L59: https://sustainability.pttep.com/en/document/sustainability-reports | M59: No | O59: =IF(N59<>"",N59,G59) -> 0 | P59: Automated retrieval found a potentially relevant page, but the captured evidence did not contain all strict coding elements together. Conservatively coded 0 pending researcher verification.
A60: Thai Main Sample | B60: PTTEP | C60: 2023 | D60: Energy | E60: Q9 | F60: Measurable Progress Against Targets | G60: 0 | H60: AI preliminary 0/uncertain — researcher verification required | I60: PTTEP 100% 75% 51% 20% 15% 50% 100% 49% 25% 49% PTT PTT Energy PTTEP PTTEPI PTTEPO Siam Digital SPSE Complex EH GHBR 25% PTTEP 75% Structure and Business Operations Services 25% PTTEP 75% TC 50% 100% 53.9496% 25.001% 100% 80% 37.0842% 100% 100% 100% 100% 100% 100% 100% 100% 25% PTTEP 75% B8/32 PTTEP PTTEP PTTEP PTTEP PTTEP PTTEP PTTEP HK CPOC SHL Orange Partners PTTEPH ATL MGTC KV HV HL AG EP-Tech BC ED 25% SV 75% PTTEP 25% 28.5% 35% 100% NH 100% 100% PTTEP HV JOC HL JOC GBRS MENA PTTEP PGH HKO 50% Natuna 2 B.V. 100% 100% 1 | J60: PTTEP one report 2023.pdf | K60: p. 63 | L60: https://sustainability.pttep.com/en/document/sustainability-reports | M60: No | O60: =IF(N60<>"",N60,G60) -> 0 | P60: Quantitative emissions are present but measurable progress against a target/baseline/pathway was not sufficiently evidenced. | AI-assisted evidence retrieval; not yet personally verified by the researcher.
A61: Thai Main Sample | B61: PTTEP | C61: 2023 | D61: Energy | E61: Q10 | F61: Independent External Assurance | G61: 0 | H61: AI preliminary 0/uncertain — researcher verification required | I61: 56-1 One Report / Annual Report 2023 Sustainability Report Incorporated PTT Exploration and Production Public Company Limited 216 6.3.4 The Independent Directors Committee Report to the performance of the Board of Directors’ duties in 2023. Independent directors provided valuable opinions, Independent directors play a significant role in ensuring promoting transparency in both Board of Directors’ the best interests of the Company, shareholders, and meetings and subcommittees’ meetings. In the event that stakeholders. They ensure governance, policies, and a director is shown to have a conflict of interest with any strategies implementation, together wit | J61: PTTEP one report 2023.pdf | K61: p. 206 | L61: https://sustainability.pttep.com/en/document/sustainability-reports | M61: No | O61: =IF(N61<>"",N61,G61) -> 0 | P61: External audit/assurance language was found, but coverage of relevant GHG/climate data was not sufficiently clear. | AI-assisted evidence retrieval; not yet personally verified by the researcher.
A62: Thai Main Sample | B62: PTTEP | C62: 2024 | D62: Energy | E62: Q1 | F62: Time-Bound Net-Zero Target | G62: 1 | H62: 2024 pilot evidence pass: Verified | I62: PTTEP states Net Zero GHG Emissions for its E&P business by 2050, covering Scope 1 and 2 under operational control. | J62: PTTEP TCFD Report 2024 | K62: p.27 | L62: https://sustainability.pttep.com/storage/document/sustainability/pttep-tcfd-disclosure-report-en.pdf | M62: No | O62: =IF(N62<>"",N62,G62) -> 1 | P62: Explicit target and year. | Imported from the earlier 2024 evidence workbook; researcher personal verification is still required before treating this as final dissertation coding.
A63: Thai Main Sample | B63: PTTEP | C63: 2024 | D63: Energy | E63: Q2 | F63: Measurable Interim Emissions-Reduction Target | G63: 1 | H63: 2024 pilot evidence pass: Verified | I63: PTTEP targets a 30% reduction in GHG emissions intensity by 2030 and 50% by 2040 from 2020. | J63: PTTEP TCFD Report 2024 | K63: p.27 | L63: https://sustainability.pttep.com/storage/document/sustainability/pttep-tcfd-disclosure-report-en.pdf | M63: No | O63: =IF(N63<>"",N63,G63) -> 1 | P63: Quantitative interim target with baseline and target years. | Imported from the earlier 2024 evidence workbook; researcher personal verification is still required before treating this as final dissertation coding.
A64: Thai Main Sample | B64: PTTEP | C64: 2024 | D64: Energy | E64: Q3 | F64: SBTi-Validated Target | G64: 0 | H64: 2024 pilot evidence pass: Conservative 0 / dashboard recheck | I64: No validated entity-level SBTi target was confirmed for the 2024 observation. | J64: SBTi Target Dashboard | K64: Search PTTEP | L64: https://sciencebasedtargets.org/target-dashboard | M64: No | O64: =IF(N64<>"",N64,G64) -> 0 | P64: Oil & gas sector context and absence of confirmed validation; conservative 0. | Imported from the earlier 2024 evidence workbook; researcher personal verification is still required before treating this as final dissertation coding.
A65: Thai Main Sample | B65: PTTEP | C65: 2024 | D65: Energy | E65: Q4 | F65: Quantitative Scope 1 and Scope 2 Disclosure | G65: 1 | H65: 2024 pilot evidence pass: Verified | I65: PTTEP reports Scope 1 and Scope 2 emissions quantitatively in MtCO2e. | J65: PTTEP TCFD Report 2024 | K65: p.30 | L65: https://sustainability.pttep.com/storage/document/sustainability/pttep-tcfd-disclosure-report-en.pdf | M65: No | O65: =IF(N65<>"",N65,G65) -> 1 | P65: Quantitative Scope 1 and 2 with units. | Imported from the earlier 2024 evidence workbook; researcher personal verification is still required before treating this as final dissertation coding.
A66: Thai Main Sample | B66: PTTEP | C66: 2024 | D66: Energy | E66: Q5 | F66: Quantitative Scope 3 Disclosure | G66: 1 | H66: 2024 pilot evidence pass: Verified | I66: PTTEP reports quantitative Scope 3 emissions in its annual emissions breakdown. | J66: PTTEP TCFD Report 2024 | K66: p.30 | L66: https://sustainability.pttep.com/storage/document/sustainability/pttep-tcfd-disclosure-report-en.pdf | M66: No | O66: =IF(N66<>"",N66,G66) -> 1 | P66: Quantitative Scope 3 disclosed. | Imported from the earlier 2024 evidence workbook; researcher personal verification is still required before treating this as final dissertation coding.
A67: Thai Main Sample | B67: PTTEP | C67: 2024 | D67: Energy | E67: Q6 | F67: Comparable Multi-Year Emissions Data | G67: 1 | H67: 2024 pilot evidence pass: Verified | I67: PTTEP presents comparable Scope 1, 2 and 3 data for 2020-2023 in the TCFD report and 2024 reporting is incorporated in One Report. | J67: PTTEP TCFD / Annual reporting | K67: p.30 + 2024 One Report | L67: https://sustainability.pttep.com/en/document/sustainability-reports | M67: No | O67: =IF(N67<>"",N67,G67) -> 1 | P67: Multi-year disclosure is established; 2024 source should be retained in final evidence log. | Imported from the earlier 2024 evidence workbook; researcher personal verification is still required before treating this as final dissertation coding.
A68: Thai Main Sample | B68: PTTEP | C68: 2024 | D68: Energy | E68: Q7 | F68: Transition Implementation & Resource Allocation | G68: 1 | H68: 2024 pilot evidence pass: Verified | I68: PTTEP applies internal carbon pricing of USD 35-60/tCO2e in investment decisions and allocates transition capital. | J68: PTTEP TCFD Report 2024 | K68: p.20 | L68: https://sustainability.pttep.com/storage/document/sustainability/pttep-tcfd-disclosure-report-en.pdf | M68: No | O68: =IF(N68<>"",N68,G68) -> 1 | P68: Explicit financial decision resource linked to transition. | Imported from the earlier 2024 evidence workbook; researcher personal verification is still required before treating this as final dissertation coding.
... A75: Thai Main Sample | B75: PTTEP | C75: 2025 | D75: Energy | E75: Q4 | F75: Quantitative Scope 1 and Scope 2 Disclosure | G75: 1 | H75: AI evidence found — researcher verification required | I75: h the energy transition. In response, the Company has announced a target to achieve Net Zero Greenhouse Gas (GHG) Emissions by 2050, supporting a sustainable transition and climate action. The target covers both direct (Scope 1) and indirect (Scope 2) emissions from the E&P business under PTTEP’s operational control. The interim targets have also been established to reduce GHG emissions intensity by at least 30% by 2030 and 50% by 2040, compared to the 2020 base year. Reduced GHG emissions Achieved cumulative forest over 568,000 tonnes conservation and restoration of CO2 equivalent through over 156,000 rai of land emissions reduction initiatives across PTTEP’s operations. Reduced GHG emissions intensity Increased cumulative income | J75: PTTEP one report 2025.pdf | K75: p. 265 | L75: https://sustainability.pttep.com/en/document/sustainability-reports | M75: No | O75: =IF(N75<>"",N75,G75) -> 1 | P75: Quantitative Scope 1 and Scope 2 emissions are disclosed with numerical data. | AI-assisted evidence retrieval; not yet personally verified by the researcher.
A76: Thai Main Sample | B76: PTTEP | C76: 2025 | D76: Energy | E76: Q5 | F76: Quantitative Scope 3 Disclosure | G76: 0 | H76: AI preliminary 0/uncertain — researcher verification required | I76: No qualifying evidence found in selected report(s). | J76: PTTEP one report 2025.pdf | L76: https://sustainability.pttep.com/en/document/sustainability-reports | M76: No | O76: =IF(N76<>"",N76,G76) -> 0 | P76: No qualifying evidence found under the strict coding rule. | AI-assisted evidence retrieval; not yet personally verified by the researcher.
A77: Thai Main Sample | B77: PTTEP | C77: 2025 | D77: Energy | E77: Q6 | F77: Comparable Multi-Year Emissions Data | G77: 0 | H77: AI preliminary 0/uncertain — researcher verification required | I77: T Exploration and Production Public Company Limited Financial Highlights 11 Financial Highlights Financial Highlights Total assets Total liabilities Total equity Total revenues Profit for the year – Owners of the parent 2023 2024 2025 (USD million) 29,571 Dividend per share (THB) 9.50 9.625 8.75* 28,401 30,000 Dividend yield (%)** 6.35 8.09 7.74 26,380 * Total dividend of 2025 at the rate of THB 8.75 per share includes the interim dividend at the rate of THB 4.10 per share and the second 25,000 half-year dividend at the rate of THB 4.65 per share. Payments of the interim dividend and the second half-year dividend will be proposed in 2026 General Shareholder’s Meeting on March 30, 2026, for acknowledgement and approval, respectivel | J77: PTTEP one report 2025.pdf | K77: p. 7 | L77: https://sustainability.pttep.com/en/document/sustainability-reports | M77: No | O77: =IF(N77<>"",N77,G77) -> 0 | P77: A multi-year emissions series was not sufficiently evidenced on the selected disclosure. | AI-assisted evidence retrieval; not yet personally verified by the researcher.
A78: Thai Main Sample | B78: PTTEP | C78: 2025 | D78: Energy | E78: Q7 | F78: Transition Implementation & Resource Allocation | G78: 0 | H78: AI conservative 0 — evidence snippet did not satisfy all strict rule elements; researcher recheck recommended | I78: loration and Production Public Company Limited Structure and Business Operations 45 Business Overview Phase Exploration Development Production PTTEP Group’s core business is the exploration and production • Vietnam 16-1 Project UAE14 Participation Interest 28.5% of petroleum in Thailand and overseas. As of December 31, Operator: HL JOC • Ghasha Concession Project 2025, PTTEP Group had petroleum exploration and production Kazakhstan Participation Interest 10% • Vietnam B and 48/95 Operator: ADNOC projects in 10 countries1, 2 with details as follows: Algeria Project Participation Interest 8.5% • Abu Dhabi Offshore 2 UAE Myanmar Project15 Operator: Vietnam National Thailand3, 4 • E5 Project7 Oman Vietnam Industry – Energy Group Parti | J78: PTTEP one report 2025.pdf | K78: p. 34 | L78: https://sustainability.pttep.com/en/document/sustainability-reports | M78: No | O78: =IF(N78<>"",N78,G78) -> 0 | P78: Automated retrieval found a potentially relevant page, but the captured evidence did not contain all strict coding elements together. Conservatively coded 0 pending researcher verification.
A79: Thai Main Sample | B79: PTTEP | C79: 2025 | D79: Energy | E79: Q8 | F79: Board-Level Climate Oversight | G79: 1 | H79: AI evidence found — researcher verification required | I79: 176 Governance Structure and Key Data on the Board of Directors, Sub-Committees, Management, Employees, and Others 56-1 One Report / Annual Report 2025 Sustainability Report Incorporated PTT Exploration and Production Public Company Limited must withdraw from participation or abstain from the E&P business while upholding the best interests of voting, and subsequently inform the authority of such the Company. The CEO’s delegation of authority matter. This has been stipulated in the Company’s is permitted except in cases where the concerned Business Ethics, whi | J79: PTTEP one report 2025.pdf | K79: p. 165 | L79: https://sustainability.pttep.com/en/document/sustainability-reports | M79: No | O79: =IF(N79<>"",N79,G79) -> 1 | P79: Board or board-level committee has explicit oversight/responsibility for climate or sustainability matters. | AI-assisted evidence retrieval; not yet personally verified by the researcher.
A80: Thai Main Sample | B80: PTTEP | C80: 2025 | D80: Energy | E80: Q9 | F80: Measurable Progress Against Targets | G80: 0 | H80: AI preliminary 0/uncertain — researcher verification required | I80: 76 Structure and Business Operations 56-1 One Report / Annual Report 2025 Sustainability Report Incorporated PTT Exploration and Production Public Company Limited PTTEP 100% 15% PTTEPI SPSE 75% PTTEP 25% 100% PKC PTT 20% Services Digital 75% PTTEP 25% 100% 49% TC PANG GHBR 50% 100% CPOC PSC 25% 75% PTTEP 100% PGC 2% AGP HK 100% 100% 5% PGH 99.99833% POC POHOL 100% PTTEP 0.00167% PTTEP 5% GISCO HKO MEP 100% PTTEP 2% OLNG 36.8% QLNG SBO 100% PTTEP 2% PDO 99.99% PDO-S SKO 100% PH 100% EPG Energy 75% 5.23% 25% PTTEP 50% Natuna 94.77% PHT NH Partners 100% PTTEP 21.09% 25% BI 75% PTTEPO 25.001% B8/32 6.09% 38.99% Partners 100% SHL 100% PTTEP APICO 100% APICO 100% APICO SP 33.83% KH KL 100% | J80: PTTEP one report 2025.pdf | K80: p. 65 | L80: https://sustainability.pttep.com/en/document/sustainability-reports | M80: No | O80: =IF(N80<>"",N80,G80) -> 0 | P80: Quantitative emissions are present but measurable progress against a target/baseline/pathway was not sufficiently evidenced. | AI-assisted evidence retrieval; not yet personally verified by the researcher.
A81: Thai Main Sample | B81: PTTEP | C81: 2025 | D81: Energy | E81: Q10 | F81: Independent External Assurance | G81: 0 | H81: AI preliminary 0/uncertain — researcher verification required | I81: port 2025 Sustainability Report Incorporated PTT Exploration and Production Public Company Limited Governance Structure and Key Data on the Board of Directors, Sub-Committees, Management, Employees, and Others 187 5.3.5 Independent Directors Committee The Independent Directors Committee has the duties and responsibilities to the Board of Directors in accordance with its charter as follows: 1) To propose to the Board and/or the CEO (as applicable) significant matters that are beneficial to the Company as well as to its major and minor shareholders. 2) To advise the Board of Directors on the roles and duties that should be practiced and to provide advice on the roles and duties of independent directors that should be practiced for t | J81: PTTEP one report 2025.pdf | K81: p. 176 | L81: https://sustainability.pttep.com/en/document/sustainability-reports | M81: No | O81: =IF(N81<>"",N81,G81) -> 0 | P81: External audit/assurance language was found, but coverage of relevant GHG/climate data was not sufficiently clear. | AI-assisted evidence retrieval; not yet personally verified by the researcher.
A82: Thai Main Sample | B82: GPSC | C82: 2022 | D82: Energy | E82: Q1 | F82: Time-Bound Net-Zero Target | G82: 0 | H82: AI conservative 0 — evidence snippet did not satisfy all strict rule elements; researcher recheck recommended | I82: Clean Energy Towards Net Zero Carbon Capture, Utilization, and Storage (CCUS/CCS) Research and Development Clean energy trends and heightened awareness of the impact of global warming have significant repercussions 0 on the electric power industry. To this end, GPSC has formulated strategies to “strive towards a low-carbon and net zero electricity business” in order to cope with energy transition and minimize impacts. GPSC also seeks to create business opportunities through the S2: Scale-up Green Energy strategy and climate change stra | J82: GPSC Intergrated sustainability report 2022.pdf | K82: p. 24 | L82: https://www.gpscgroup.com/en/downloads/sd-report | M82: No | O82: =IF(N82<>"",N82,G82) -> 0 | P82: Automated retrieval found a potentially relevant page, but the captured evidence did not contain all strict coding elements together. Conservatively coded 0 pending researcher verification.
A83: Thai Main Sample | B83: GPSC | C83: 2022 | D83: Energy | E83: Q2 | F83: Measurable Interim Emissions-Reduction Target | G83: 0 | H83: AI preliminary 0/uncertain — researcher verification required | I83: nagement Net Energy Generated Installed Capacity Other KPIs "Subsidiaries & Share Operational Country Association Associated companies" holding control Thailand Global Power Synergy Public Company Limited (GPSC) GPSC 100% Yes      Combined Heat and Power Producing Company Limited GPSC 100% Yes  -   - Ratchaburi Power Company Limited GPSC 15% No  -   - Siam Solar Energy 1 Company Limited GPSC 40% No  -   - Nava Nakorn Electricity Generating Company Limited GPSC 30% No  -   - IRPC Clean Power Company Limited GPSC 51% No  -   - Bangpa-In Cogeneration Company Limited GPSC 25% No  -   - Business Services Alliance Company Limited GPSC 25% No  -   - Energy Recovery Unit Company Limited GPSC 100% Yes  -    N. | J83: GPSC Intergrated sustainability report 2022.pdf | K83: p. 64 | L83: https://www.gpscgroup.com/en/downloads/sd-report | M83: No | O83: =IF(N83<>"",N83,G83) -> 0 | P83: Quantitative target wording did not clearly contain all three required elements: magnitude, target year and baseline/reference point. | AI-assisted evidence retrieval; not yet personally verified by the researcher.
A84: Thai Main Sample | B84: GPSC | C84: 2022 | D84: Energy | E84: Q3 | F84: SBTi-Validated Target | G84: 0 | H84: AI preliminary 0/uncertain — researcher verification required | I84: The assurance comprised a combination of pre-assurance research, interviews with relevant employees, superintendents and the management. Documentation reviewed and recorded were carried out onsit visit and remotely. The validation with external bodies and/or stakeholders where relevant and interview the person in charge of producing the report were also carried out remotely for the same reason. LIMITATIONS AND MITIGATION Financial data drawn directly from independently audited financial accounts has not been checked back to source as part of this assurance process. Some statements and data within the scope were not assured due to lack of accessible records during the time scale allowed for assurance, and these are clearly marked t | J84: GPSC Intergrated sustainability report 2022.pdf | K84: p. 67 | L84: https://www.gpscgroup.com/en/downloads/sd-report | M84: No | O84: =IF(N84<>"",N84,G84) -> 0 | P84: No official SBTi validation applicable to the observation year was evidenced; alignment, commitment, submission or later validation does not qualify. | AI-assisted evidence retrieval; not yet personally verified by the researcher.
A85: Thai Main Sample | B85: GPSC | C85: 2022 | D85: Energy | E85: Q4 | F85: Quantitative Scope 1 and Scope 2 Disclosure | G85: 1 | H85: AI evidence found — researcher verification required | I85: al Capital • Employee innovators: 25 persons G • ESS R&D budget: THB 93.07 MM Productivity Natural Capital • Net energy generated: 28.07 TWh • Water withdrawal: • Renewable energy generated: 44,612.08 MWh 1,800.79 Mm3 • Scope 1 GHG emissions: 12.68 million tCO2e • Energy consumption • Scope 2 GHG emissions: 27,850.95 tCO2e 24.87 MWh • GHG emission intensity: 0.45 tCO2e /MWh • Employees in the Environment • Total water discharge: 1,765.7 Mm3 Department: 29 persons • Total waste landfilling: 9,929.07 tons 12 GLOBAL POWER SYNERGY PUBLIC COMPANY LIMITED | J85: GPSC Intergrated sustainability report 2022.pdf | K85: p. 12 | L85: https://www.gpscgroup.com/en/downloads/sd-report | M85: No | O85: =IF(N85<>"",N85,G85) -> 1 | P85: Quantitative Scope 1 and Scope 2 emissions are disclosed with numerical data. | AI-assisted evidence retrieval; not yet personally verified by the researcher.
A86: Thai Main Sample | B86: GPSC | C86: 2022 | D86: Energy | E86: Q5 | F86: Quantitative Scope 3 Disclosure | G86: 1 | H86: AI evidence found — researcher verification required | I86: nsumption GPSC Warehouse 305-1 Direct (Scope 1) GHG emissions Central Utility Plant 1 : CUP-1 305-2 Energy indirect (Scope 2) GHG emissions Central Utility Plant 2 : CUP-2 Central Utility Plant 3 : CUP-3 Other indirect (Scope 3) GHG emissions (Upstream categories) Central Utility Plant 4 : CUP-4 305-3 3. Fuel and energy related activities Sriracha Power Plant Glow IPP plant 4. Upstream transportation and distribution Glow Energy Phase 1 plant 5. Waste generated in operations Glow Energy Phase 2 plant 305-4 GHG emissions intensity Nitrogen Oxides (NOx), Sulfur Oxides (SOx), and other Glow Energy Phase 4 plant significant air emissions Glow Energy Phase 5 plant 305-7 (Including direct Mercury emission, dust emission, SF6 emission) G | J86: GPSC Intergrated sustainability report 2022.pdf | K86: p. 67 | L86: https://www.gpscgroup.com/en/downloads/sd-report | M86: No | O86: =IF(N86<>"",N86,G86) -> 1 | P86: Quantitative Scope 3 emissions (including financed emissions where relevant) are disclosed. | AI-assisted evidence retrieval; not yet personally verified by the researcher.
A87: Thai Main Sample | B87: GPSC | C87: 2022 | D87: Energy | E87: Q6 | F87: Comparable Multi-Year Emissions Data | G87: 0 | H87: AI conservative 0 — evidence snippet did not satisfy all strict rule elements; researcher recheck recommended | I87: INTEGRATED SUSTAINABILITY REPORT 2022 Outcomes Investors Government agencies Customers Shareholders Suppliers Partners Society Impact to stakeholders • Had 38% power generated from renewables and value creation • Reduced GHG emissions by 294,505 tCO2e from the use of renewable energy and reduced fuel consumption by 7.40 MMBtu • Reduced energy consumption by 2.17 million MWh • Had GHG emission intensity of 0.45 kgCO2e/kWh • Reduced GHG emissions under T-VER by 433,122 tCO2e • Won an award under the Low Carbon and Sustainable Business (LCSB) Project | J87: GPSC Intergrated sustainability report 2022.pdf | K87: p. 23 | L87: https://www.gpscgroup.com/en/downloads/sd-report | M87: No | O87: =IF(N87<>"",N87,G87) -> 0 | P87: Automated retrieval found a potentially relevant page, but the captured evidence did not contain all strict coding elements together. Conservatively coded 0 pending researcher verification.
A88: Thai Main Sample | B88: GPSC | C88: 2022 | D88: Energy | E88: Q7 | F88: Transition Implementation & Resource Allocation | G88: 0 | H88: AI conservative 0 — evidence snippet did not satisfy all strict rule elements; researcher recheck recommended | I88: announced its target to achieve net zero GHG emissions by 2060 and formulated the S2: Scale-up Green Energy strategy. In addition, in making preparations to become a leading global power producer, GPSC has increased its investments in order to increase its use of renewable energy and reduce power generation based on fossil fuels, while also maintaining its reliable and secure energy delivery, which is GPSC’s strength and an area where the Company can satisfy stakeholder expectations efficiently. Based on the strategies described above, GPSC aims to increase renewables-based power production to 38% by 2025 and to over 50% by 2030. In 2022, the Company invested into two large renewables projects, namely a solar power plant in India | J88: GPSC Intergrated sustainability report 2022.pdf | K88: p. 28 | L88: https://www.gpscgroup.com/en/downloads/sd-report | M88: No | O88: =IF(N88<>"",N88,G88) -> 0 | P88: Automated retrieval found a potentially relevant page, but the captured evidence did not contain all strict coding elements together. Conservatively coded 0 pending researcher verification.
... A93: Thai Main Sample | B93: GPSC | C93: 2023 | D93: Energy | E93: Q2 | F93: Measurable Interim Emissions-Reduction Target | G93: 0 | H93: AI preliminary 0/uncertain — researcher verification required | I93: ergy Generated Compliance (GRC) Installed Capacity Other KPIs Subsidiaries & Share Operational Country Association Associated companies holding control Thailand Global Power Synergy Public Company Limited (GPSC) GPSC 100% Yes Combined Heat and Power Producing Company Limited GPSC 100% Yes - - Ratchaburi Power Company Limited GPSC 15% No - - Siam Solar Energy 1 Company Limited GPSC 40% No - - Nava Nakorn Electricity Generating Company Limited GPSC 30% No - - IRPC Clean Power Company Limited GPSC 51% No - - Bangpa-In Cogeneration Company Limited GPSC 25% No - - Business Services Alliance Company Limited GPSC 25% No - Energy Recovery Unit Company Limited GPSC 100% Yes - - N.P.S. Star Group Company Limited GPSC 50% No - - World X Chan | J93: GPSC Intergrated sustainability report 2023.pdf | K93: p. 54 | L93: https://www.gpscgroup.com/en/downloads/sd-report | M93: No | O93: =IF(N93<>"",N93,G93) -> 0 | P93: Quantitative target wording did not clearly contain all three required elements: magnitude, target year and baseline/reference point. | AI-assisted evidence retrieval; not yet personally verified by the researcher.
A94: Thai Main Sample | B94: GPSC | C94: 2023 | D94: Energy | E94: Q3 | F94: SBTi-Validated Target | G94: 0 | H94: AI preliminary 0/uncertain — researcher verification required | I94: No explicit SBTi validation statement found in the selected reports. | J94: GPSC Intergrated sustainability report 2023.pdf | L94: https://www.gpscgroup.com/en/downloads/sd-report | M94: No | O94: =IF(N94<>"",N94,G94) -> 0 | P94: No official SBTi validation applicable to the observation year was evidenced; alignment, commitment, submission or later validation does not qualify. | AI-assisted evidence retrieval; not yet personally verified by the researcher.
A95: Thai Main Sample | B95: GPSC | C95: 2023 | D95: Energy | E95: Q4 | F95: Quantitative Scope 1 and Scope 2 Disclosure | G95: 1 | H95: AI evidence found — researcher verification required | I95: tensity (Scope1 and Supply Chain Management Direct Mercury Emission Sustainable Community Energy Consumption Ash& Gypsum Waste Water Consumption Hazardous Waste Waste Disposal Dust Emission Nox Emission Sox Emission GHG Scope 1 GHG Scope 2 GHG Scope 3 Market (OHS) SF6 2) - - - - - - - - - - - - - - - - - - - - - - - - - - - - - - - - - - - - - - - - - - - - - - - - - - - - - - - - - - - - - - - - - - - - - - - - - - - - - - - - - - - - - - - - - - - - - - - - - - - - - - - - - - - - - - - - - - - - - - - - - - - - - - - - - - - - - - - - - - - - - - - - - - - - - - - - - - - - - - - - - - - - - - - - - - - - - - - - - - - - - - - - - - - - - - - - - - - - - - - - - - - - - - - - - - - - - - - - - - - - - - - - - - - - - - - - - - | J95: GPSC Intergrated sustainability report 2023.pdf | K95: p. 55 | L95: https://www.gpscgroup.com/en/downloads/sd-report | M95: No | O95: =IF(N95<>"",N95,G95) -> 1 | P95: Quantitative Scope 1 and Scope 2 emissions are disclosed with numerical data. | AI-assisted evidence retrieval; not yet personally verified by the researcher.
A96: Thai Main Sample | B96: GPSC | C96: 2023 | D96: Energy | E96: Q5 | F96: Quantitative Scope 3 Disclosure | G96: 1 | H96: AI evidence found — researcher verification required | I96: ly Chain Management Direct Mercury Emission Sustainable Community Energy Consumption Ash& Gypsum Waste Water Consumption Hazardous Waste Waste Disposal Dust Emission Nox Emission Sox Emission GHG Scope 1 GHG Scope 2 GHG Scope 3 Market (OHS) SF6 2) - - - - - - - - - - - - - - - - - - - - - - - - - - - - - - - - - - - - - - - - - - - - - - - - - - - - - - - - - - - - - - - - - - - - - - - - - - - - - - - - - - - - - - - - - - - - - - - - - - - - - - - - - - - - - - - - - - - - - - - - - - - - - - - - - - - - - - - - - - - - - - - - - - - - - - - - - - - - - - - - - - - - - - - - - - - - - - - - - - - - - - - - - - - - - - - - - - - - - - - - - - - - - - - - - - - - - - - - - - - - - - - - - - - - - - - - - - - - - - - - - - - - - - | J96: GPSC Intergrated sustainability report 2023.pdf | K96: p. 55 | L96: https://www.gpscgroup.com/en/downloads/sd-report | M96: No | O96: =IF(N96<>"",N96,G96) -> 1 | P96: Quantitative Scope 3 emissions (including financed emissions where relevant) are disclosed. | AI-assisted evidence retrieval; not yet personally verified by the researcher.
A97: Thai Main Sample | B97: GPSC | C97: 2023 | D97: Energy | E97: Q6 | F97: Comparable Multi-Year Emissions Data | G97: 0 | H97: AI preliminary 0/uncertain — researcher verification required | I97: Key Result Key Result Key Result Key Result Investigation on development Higher reduction of GHG Reduction of GHG emissions by Share of renewable power and application of emissions from the 2022 level 590 tons of carbon dioxide at 65% to 2,161.38 MW, by 47.09%, totalled equivalent through the up from 45.45% recorded CCS/CCUS forestation of 46,000 trees in 2022. technologies with other 124,768 tons in 149 rai and 9,600 seagrass of carbon dioxide equivalent. organizations. in 6 rai. * Higher GHG emissions reflected higher power generation to meet higher demand. The GHG emission concentration is, however, dropping by 7.68% from the 2022 level as a result of the higher efficiency of generating processes. | J97: GPSC Intergrated sustainability report 2023.pdf | K97: p. 23 | L97: https://www.gpscgroup.com/en/downloads/sd-report | M97: No | O97: =IF(N97<>"",N97,G97) -> 0 | P97: A multi-year emissions series was not sufficiently evidenced on the selected disclosure. | AI-assisted evidence retrieval; not yet personally verified by the researcher.
A98: Thai Main Sample | B98: GPSC | C98: 2023 | D98: Energy | E98: Q7 | F98: Transition Implementation & Resource Allocation | G98: 1 | H98: AI evidence found — researcher verification required | I98: ources by over 50% by 2030, primarily from solar stands at 9,525 MW (up from 4,364 MW in 2022 or by energy. With high-potential power generation from solar more than twice). This capacity can be constantly and available investment opportunities in India, the company increased under India’s national energy policy to generate invested through the share acquisition of Avaada Energy more than 500 gigawatts of power from renewable sources Private Limited (AVAADA), intended to support its business by 2030 toward the fully integrated clean energy and target. As one of the five top solar power generation generation of carbon credit in the future. In addition, GPSC countries, the geography and climate of India are entered investment cooper | J98: GPSC Intergrated sustainability report 2023.pdf | K98: p. 28 | L98: https://www.gpscgroup.com/en/downloads/sd-report | M98: No | O98: =IF(N98<>"",N98,G98) -> 1 | P98: Concrete transition action is linked to a measurable financial or operational resource allocation. | AI-assisted evidence retrieval; not yet personally verified by the researcher.
A99: Thai Main Sample | B99: GPSC | C99: 2023 | D99: Energy | E99: Q8 | F99: Board-Level Climate Oversight | G99: 0 | H99: AI preliminary 0/uncertain — researcher verification required | I99: rends. After all, GPSC’s past successes may no longer be its future successes undertraditional business, which is increasingly facing disruption.” Somchai Meesen Independent director / Chairman, Corporate Governance and Sustainability Committee / Member, Audit Com- mittee (non-executive director) Investors “GPSC belongs to a critical business sector for “As a national and international energy industry national growth and national achievement of the leader in sustainability operation, GPSC is also a Carbon Neutral and Net Zero goals. Today, it is role model for small and medium industries for not only a leader and a role model for domestic applying lessons learned to their adjustment in and international sustainability operation, b | J99: GPSC Intergrated sustainability report 2023.pdf | K99: p. 52 | L99: https://www.gpscgroup.com/en/downloads/sd-report | M99: No | O99: =IF(N99<>"",N99,G99) -> 0 | P99: Governance is described but explicit board-level climate/sustainability oversight was not sufficiently evidenced. | AI-assisted evidence retrieval; not yet personally verified by the researcher.
A100: Thai Main Sample | B100: GPSC | C100: 2023 | D100: Energy | E100: Q9 | F100: Measurable Progress Against Targets | G100: 0 | H100: AI preliminary 0/uncertain — researcher verification required | I100: ergy Generated Compliance (GRC) Installed Capacity Other KPIs Subsidiaries & Share Operational Country Association Associated companies holding control Thailand Global Power Synergy Public Company Limited (GPSC) GPSC 100% Yes Combined Heat and Power Producing Company Limited GPSC 100% Yes - - Ratchaburi Power Company Limited GPSC 15% No - - Siam Solar Energy 1 Company Limited GPSC 40% No - - Nava Nakorn Electricity Generating Company Limited GPSC 30% No - - IRPC Clean Power Company Limited GPSC 51% No - - Bangpa-In Cogeneration Company Limited GPSC 25% No - - Business Services Alliance Company Limited GPSC 25% No - Energy Recovery Unit Company Limited GPSC 100% Yes - - N.P.S. Star Group Company Limited GPSC 50% No - - World X Chan | J100: GPSC Intergrated sustainability report 2023.pdf | K100: p. 54 | L100: https://www.gpscgroup.com/en/downloads/sd-report | M100: No | O100: =IF(N100<>"",N100,G100) -> 0 | P100: Quantitative emissions are present but measurable progress against a target/baseline/pathway was not sufficiently evidenced. | AI-assisted evidence retrieval; not yet personally verified by the researcher.
A101: Thai Main Sample | B101: GPSC | C101: 2023 | D101: Energy | E101: Q10 | F101: Independent External Assurance | G101: 0 | H101: AI preliminary 0/uncertain — researcher verification required | I101: Key Result Key Result Key Result Key Result Investigation on development Higher reduction of GHG Reduction of GHG emissions by Share of renewable power and application of emissions from the 2022 level 590 tons of carbon dioxide at 65% to 2,161.38 MW, by 47.09%, totalled equivalent through the up from 45.45% recorded CCS/CCUS forestation of 46,000 trees in 2022. technologies with other 124,768 tons in 149 rai and 9,600 seagrass of carbon dioxide equivalent. organizations. in 6 rai. * Higher GHG emissions reflected higher power generation to meet higher demand. The GHG emission concentration is, however, dro | J101: GPSC Intergrated sustainability report 2023.pdf | K101: p. 23 | L101: https://www.gpscgroup.com/en/downloads/sd-report | M101: No | O101: =IF(N101<>"",N101,G101) -> 0 | P101: External audit/assurance language was found, but coverage of relevant GHG/climate data was not sufficiently clear. | AI-assisted evidence retrieval; not yet personally verified by the researcher.
A102: Thai Main Sample | B102: GPSC | C102: 2024 | D102: Energy | E102: Q1 | F102: Time-Bound Net-Zero Target | G102: 1 | H102: 2024 pilot evidence pass: Verified | I102: GPSC states a long-term target of carbon neutrality by 2050 and net-zero GHG emissions by 2060. | J102: GPSC Integrated Sustainability Report 2024 | K102: Climate target section | L102: https://www.gpscgroup.com/storage/download/sd-report/20250513-gpsc-sd2024-en.pdf | M102: No | O102: =IF(N102<>"",N102,G102) -> 1 | P102: Explicit net-zero target and year. | Imported from the earlier 2024 evidence workbook; researcher personal verification is still required before treating this as final dissertation coding.
A103: Thai Main Sample | B103: GPSC | C103: 2024 | D103: Energy | E103: Q2 | F103: Measurable Interim Emissions-Reduction Target | G103: 1 | H103: 2024 pilot evidence pass: Verified | I103: GPSC targets a 35% reduction in GHG emissions intensity by 2030 from a 2020 base year. | J103: GPSC Sustainability / Materiality targets | K103: Target section | L103: https://www.gpscgroup.com/en/sustainability/gpsc-sustainability/materiality-assessment | M103: No | O103: =IF(N103<>"",N103,G103) -> 1 | P103: Quantitative target, target year and baseline. | Imported from the earlier 2024 evidence workbook; researcher personal verification is still required before treating this as final dissertation coding.
A104: Thai Main Sample | B104: GPSC | C104: 2024 | D104: Energy | E104: Q3 | F104: SBTi-Validated Target | G104: 0 | H104: 2024 pilot evidence pass: Conservative 0 / dashboard recheck | I104: No entity-level SBTi validation was confirmed for GPSC for the 2024 observation. | J104: SBTi Target Dashboard | K104: Search GPSC | L104: https://sciencebasedtargets.org/target-dashboard | M104: No | O104: =IF(N104<>"",N104,G104) -> 0 | P104: Conservative strict rule. | Imported from the earlier 2024 evidence workbook; researcher personal verification is still required before treating this as final dissertation coding.
A105: Thai Main Sample | B105: GPSC | C105: 2024 | D105: Energy | E105: Q4 | F105: Quantitative Scope 1 and Scope 2 Disclosure | G105: 1 | H105: 2024 pilot evidence pass: Verified | I105: GPSC's 2024 integrated sustainability report discloses quantitative Scope 1 and Scope 2 emissions. | J105: GPSC Integrated Sustainability Report 2024 | K105: Environmental performance | L105: https://www.gpscgroup.com/storage/download/sd-report/20250513-gpsc-sd2024-en.pdf | M105: No | O105: =IF(N105<>"",N105,G105) -> 1 | P105: Quantitative scope data are disclosed. | Imported from the earlier 2024 evidence workbook; researcher personal verification is still required before treating this as final dissertation coding.
A106: Thai Main Sample | B106: GPSC | C106: 2024 | D106: Energy | E106: Q5 | F106: Quantitative Scope 3 Disclosure | G106: 1 | H106: 2024 pilot evidence pass: Verified | I106: GPSC reports Scope 3 emissions by categories including fuel- and energy-related activities. | J106: GPSC Integrated Sustainability Report 2024 | K106: Scope 3 section | L106: https://www.gpscgroup.com/storage/download/sd-report/20250513-gpsc-sd2024-en.pdf | M106: No | O106: =IF(N106<>"",N106,G106) -> 1 | P106: Quantitative material Scope 3 categories are reported. | Imported from the earlier 2024 evidence workbook; researcher personal verification is still required before treating this as final dissertation coding.
... A123: Thai Main Sample | B123: GULF | C123: 2022 | D123: Energy | E123: Q2 | F123: Measurable Interim Emissions-Reduction Target | G123: 0 | H123: AI preliminary 0/uncertain — researcher verification required | I123: Topic Unit 2019 2020 2021 2022 2022 Target Male Female Male Female Male Female Male Female Average hiring cost / FTE THB 18,000 12,500 19,000 41,229 Position Filled by Internal Candidates Percentage of open positions filled % 31 82 76 39 by internal candidates % 26 5 47 35 47 30 29 10 - Below 30 years old % 15 4 16 11 14 12 11 2 - 30-50 years old % 9 1 27 24 23 17 13 7 - Over 50 years old % 2 0 4 0 9 1 5 1 Turnover Breakdown by Age Group Total number of turnovers % 4.7 6.9 5.2 7.8 5 % 3.4 1.3 5.2 1.7 3.3 2.0 5.3 2.5 - Below 30 years old % 1.8 0.6 2.8 | J123: GULF ESG 2022.pdf | K123: p. 11 | L123: https://sustainability.gulf.co.th/en/document/sustainability-reports | M123: No | O123: =IF(N123<>"",N123,G123) -> 0 | P123: Quantitative target wording did not clearly contain all three required elements: magnitude, target year and baseline/reference point. | AI-assisted evidence retrieval; not yet personally verified by the researcher.
A124: Thai Main Sample | B124: GULF | C124: 2022 | D124: Energy | E124: Q3 | F124: SBTi-Validated Target | G124: 0 | H124: AI preliminary 0/uncertain — researcher verification required | I124: No explicit SBTi validation statement found in the selected reports. | J124: GULF Sustainability Report 2022.pdf | L124: https://sustainability.gulf.co.th/en/document/sustainability-reports | M124: No | O124: =IF(N124<>"",N124,G124) -> 0 | P124: No official SBTi validation applicable to the observation year was evidenced; alignment, commitment, submission or later validation does not qualify. | AI-assisted evidence retrieval; not yet personally verified by the researcher.
A125: Thai Main Sample | B125: GULF | C125: 2022 | D125: Energy | E125: Q4 | F125: Quantitative Scope 1 and Scope 2 Disclosure | G125: 1 | H125: AI evidence found — researcher verification required | I125: /A N/A Greenhouse Gas Emissions Total GHG emissions tCO2e 9,512,526.53 8,503,887.23 12,334,362.17 13,676,085.13 Total direct GHG emissions (Scope tCO2e 9,458,152.59 8,463,732.83 9,626,793.97 10,491,006.33 9,929,319 1) - Scope 1 intensity tCO2e / MWh 0.387 0.389 0.397 0.388 Data coverage % of power plants 100 100 100 100 which have achieved COD as of 31 December Total indirect GHG emissions tCO2e 49,921.95 36,486.44 35,516.50 110,967.82 (Scope 2) - Location-based tCO2e 49,921.95 36,486.44 35,516.50 110,967.82 68,380 - Market-based tCO2e 0 0 0 0 0 Data coverage % of power plants 100 100 100 100 which have achieved COD as of 31 December Other indirect GHG emissions tCO2e 4,451.99 3,667.96 2,672,051.70 3,074,110.98 2,735,217 (Scope 3) | J125: GULF ESG 2022.pdf | K125: p. 8 | L125: https://sustainability.gulf.co.th/en/document/sustainability-reports | M125: No | O125: =IF(N125<>"",N125,G125) -> 1 | P125: Quantitative Scope 1 and Scope 2 emissions are disclosed with numerical data. | AI-assisted evidence retrieval; not yet personally verified by the researcher.
A126: Thai Main Sample | B126: GULF | C126: 2022 | D126: Energy | E126: Q5 | F126: Quantitative Scope 3 Disclosure | G126: 1 | H126: AI evidence found — researcher verification required | I126: 2 68,380 - Market-based tCO2e 0 0 0 0 0 Data coverage % of power plants 100 100 100 100 which have achieved COD as of 31 December Other indirect GHG emissions tCO2e 4,451.99 3,667.96 2,672,051.70 3,074,110.98 2,735,217 (Scope 3) Total GHG intensity tCO2e / MWh 0.390 0.391 0.508 0.505 8 | J126: GULF ESG 2022.pdf | K126: p. 8 | L126: https://sustainability.gulf.co.th/en/document/sustainability-reports | M126: No | O126: =IF(N126<>"",N126,G126) -> 1 | P126: Quantitative Scope 3 emissions (including financed emissions where relevant) are disclosed. | AI-assisted evidence retrieval; not yet personally verified by the researcher.
A127: Thai Main Sample | B127: GULF | C127: 2022 | D127: Energy | E127: Q6 | F127: Comparable Multi-Year Emissions Data | G127: 0 | H127: AI conservative 0 — evidence snippet did not satisfy all strict rule elements; researcher recheck recommended | I127: /A N/A Greenhouse Gas Emissions Total GHG emissions tCO2e 9,512,526.53 8,503,887.23 12,334,362.17 13,676,085.13 Total direct GHG emissions (Scope tCO2e 9,458,152.59 8,463,732.83 9,626,793.97 10,491,006.33 9,929,319 1) - Scope 1 intensity tCO2e / MWh 0.387 0.389 0.397 0.388 Data coverage % of power plants 100 100 100 100 which have achieved COD as of 31 December Total indirect GHG emissions tCO2e 49,921.95 36,486.44 35,516.50 110,967.82 (Scope 2) - Location-based tCO2e 49,921.95 36,486.44 35,516.50 110,967.82 68,380 - Market-based tCO2e 0 0 0 0 0 Data coverage % of power plants 100 100 100 100 which have achieved COD as of 31 December Other indirect GHG emissions tCO2e 4,451.99 3,667.96 2,672,051.70 3,074,110.98 2,735,217 (Scope 3) | J127: GULF ESG 2022.pdf | K127: p. 8 | L127: https://sustainability.gulf.co.th/en/document/sustainability-reports | M127: No | O127: =IF(N127<>"",N127,G127) -> 0 | P127: Automated retrieval found a potentially relevant page, but the captured evidence did not contain all strict coding elements together. Conservatively coded 0 pending researcher verification.
A128: Thai Main Sample | B128: GULF | C128: 2022 | D128: Energy | E128: Q7 | F128: Transition Implementation & Resource Allocation | G128: 0 | H128: AI conservative 0 — evidence snippet did not satisfy all strict rule elements; researcher recheck recommended | I128: 13,085.76 17,344.48 sources - Natural gas GWh 9,679.76 9,684.32 13,085.76 17,344.48 - Nuclear/ Oil/ Coal/ Other non- GWh 0 0 0 0 renewables Total renewable energy sources GWh 0 334.15 356.15 362.94 - Wind GWh 0 0 0 0 - Solar GWh 0 180.07 161.45 169.99 - Biomass GWh 0 154.08 194.70 192.95 - Other GWh 0 0 0 0 Electricity Capacity 2030 Target Total installed capacity MW 1,705 2,195 3,567 5,264 13,099 Total non-renewable energy MW 1,586 1,586 2,951 4,431 10,552 capacity - Natural gas MW 1,586 1,586 2,951 4,431 10,552 - Nuclear/ Oil/ Coal/ Other non- MW 0 0 0 0 0 renewables Total renewable energy capacity MW 119 609 616 833 2,547 - Wind MW 0 465 469 647 252 - Solar MW 119 119 122 161 2,270 - Biomass MW 0 25 25 25 25 - Other MW 0 0 0 0 | J128: GULF ESG 2022.pdf | K128: p. 4 | L128: https://sustainability.gulf.co.th/en/document/sustainability-reports | M128: No | O128: =IF(N128<>"",N128,G128) -> 0 | P128: Automated retrieval found a potentially relevant page, but the captured evidence did not contain all strict coding elements together. Conservatively coded 0 pending researcher verification.
A129: Thai Main Sample | B129: GULF | C129: 2022 | D129: Energy | E129: Q8 | F129: Board-Level Climate Oversight | G129: 0 | H129: AI preliminary 0/uncertain — researcher verification required | I129: 559,960,000 2,773,290,000 4,458,596,999 5,162,585,999 - Cost of sales THB 22,791,098,413 23,702,173,831 34,388,041,471 74,710,988,352 - Income tax (expense) income THB 13,676,629 -107,278,789 -346,895,137 -1,344,139,254 Board of Directors Total board of directors Persons 11 11 10 12 Executive directors Persons 4 4 4 4 Independent directors 1 Persons 6 6 5 7 % of total directors 55 55 50 58 33.33 Other non-executive directors Persons 1 1 1 1 Female directors Persons 4 4 4 4 % of total directors 36 36 40 33 Average board meeting attendance % 91.30 91.40 97.73 98.81 Minimum attendance required % 75 75 75 75 Corruption and Bribery Number of operations assessed for Number of operating - 14 14 risks related to corruption projects in Tha | J129: GULF ESG 2022.pdf | K129: p. 1 | L129: https://sustainability.gulf.co.th/en/document/sustainability-reports | M129: No | O129: =IF(N129<>"",N129,G129) -> 0 | P129: Governance is described but explicit board-level climate/sustainability oversight was not sufficiently evidenced. | AI-assisted evidence retrieval; not yet personally verified by the researcher.
A130: Thai Main Sample | B130: GULF | C130: 2022 | D130: Energy | E130: Q9 | F130: Measurable Progress Against Targets | G130: 1 | H130: AI evidence found — researcher verification required | I130: Topic Unit 2019 2020 2021 2022 2022 Target Male Female Male Female Male Female Male Female Average hiring cost / FTE THB 18,000 12,500 19,000 41,229 Position Filled by Internal Candidates Percentage of open positions filled % 31 82 76 39 by internal candidates % 26 5 47 35 47 30 29 10 - Below 30 years old % 15 4 16 11 14 12 11 2 - 30-50 years old % 9 1 27 24 23 17 13 7 - Over 50 years old % 2 0 4 0 9 1 5 1 Turnover Breakdown by Age Group Total number of turnovers % 4.7 6.9 5.2 7.8 5 % 3.4 1.3 5.2 1.7 3.3 2.0 5.3 2.5 - Below 30 years old % 1.8 0.6 2.8 | J130: GULF ESG 2022.pdf | K130: p. 11 | L130: https://sustainability.gulf.co.th/en/document/sustainability-reports | M130: No | O130: =IF(N130<>"",N130,G130) -> 1 | P130: Quantitative actual performance is compared with a target, baseline, pathway or prior-period reference. | AI-assisted evidence retrieval; not yet personally verified by the researcher.
A131: Thai Main Sample | B131: GULF | C131: 2022 | D131: Energy | E131: Q10 | F131: Independent External Assurance | G131: 0 | H131: AI preliminary 0/uncertain — researcher verification required | I131: ctricity transmission losses % 0.56 0.49 0.53 0.51 Technical distribution losses % N/A N/A N/A N/A SAIDI transmission network Hours 3 8 6 5 SAIDI distribution network Hours N/A N/A N/A N/A Greenhouse Gas Emissions Total GHG emissions tCO2e 9,512,526.53 8,503,887.23 12,334,362.17 13,676,085.13 Total direct GHG emissions (Scope tCO2e 9,458,152.59 8,463,732.83 9,626,793.97 10,491,006.33 9,929,319 1) - Scope 1 intensity tCO2e / MWh 0.387 0.389 0.397 0.388 Data coverage % of power plants 100 100 100 100 which have achieved COD as of 31 December Total indirect GHG emissions tCO2e 49,921.95 36,486.44 35,516.50 110,967.82 (Scope 2) - Location-based tCO2e 49,921.95 36,486.44 35,516.50 110,967.82 68,380 - Market-based tCO2e 0 0 0 0 0 Data c | J131: GULF ESG 2022.pdf | K131: p. 8 | L131: https://sustainability.gulf.co.th/en/document/sustainability-reports | M131: No | O131: =IF(N131<>"",N131,G131) -> 0 | P131: External audit/assurance language was found, but coverage of relevant GHG/climate data was not sufficiently clear. | AI-assisted evidence retrieval; not yet personally verified by the researcher.
A132: Thai Main Sample | B132: GULF | C132: 2023 | D132: Energy | E132: Q1 | F132: Time-Bound Net-Zero Target | G132: 1 | H132: AI evidence found — researcher verification required | I132: er (continued) Water consumption in water-stressed areas Operations in water- Projects 13 14 14 15 stressed areas9 Total water consumption10 Mil. m3 8.33 10.79 15.43 24.68 Climate strategy Greenhouse gas (GHG) emissions Net Zero by Total GHG emissions Tonnes 3,944,773 5,109,713 8,791,140 14,624,745 2050 tCO2e / Total emissions intensity 0.401 0.406 0.389 0.469 MWh Direct emissions (scope 1) Tonnes 3,931,649 5,094,990 6,651,222 11,245,262 tCO2e / Reduce by Total scope 1 intensity 0.400 0.405 0.386 0.360 25% by 2030 MWh Indirect emissions (scope 2)11 Tonnes 10,762 10,782 53,794 23,547 tCO2e / Total scope 2 intensity 0.001 0.001 0.003 0.001 MWh Other indirect emissions Tonnes 2,363 3,941 2,758 3,355,936 (scope 3)12 tCO2e / Total scop | J132: GULF ESG 2023.pdf | K132: p. 12 | L132: https://sustainability.gulf.co.th/en/document/sustainability-reports | M132: No | O132: =IF(N132<>"",N132,G132) -> 1 | P132: Explicit time-bound company net-zero target found. | AI-assisted evidence retrieval; not yet personally verified by the researcher.
A133: Thai Main Sample | B133: GULF | C133: 2023 | D133: Energy | E133: Q2 | F133: Measurable Interim Emissions-Reduction Target | G133: 0 | H133: AI preliminary 0/uncertain — researcher verification required | I133: 624,745 2050 tCO2e / Total emissions intensity 0.401 0.406 0.389 0.469 MWh Direct emissions (scope 1) Tonnes 3,931,649 5,094,990 6,651,222 11,245,262 tCO2e / Reduce by Total scope 1 intensity 0.400 0.405 0.386 0.360 25% by 2030 MWh Indirect emissions (scope 2)11 Tonnes 10,762 10,782 53,794 23,547 tCO2e / Total scope 2 intensity 0.001 0.001 0.003 0.001 MWh Other indirect emissions Tonnes 2,363 3,941 2,758 3,355,936 (scope 3)12 tCO2e / Total scope 3 intensity 0.000 0.000 0.000 0.108 MWh SF6 emissions Tonnes 0.013 1.178 0.007 30,36213 Product stewardship Electricity transmission and distribution losses14 Transmission losses % 0.49 0.53 0.51 0.66 Distribution losses % N/A N/A N/A N/A Electricity transmission and distribution reliabili | J133: GULF ESG 2023.pdf | K133: p. 12 | L133: https://sustainability.gulf.co.th/en/document/sustainability-reports | M133: No | O133: =IF(N133<>"",N133,G133) -> 0 | P133: Quantitative target wording did not clearly contain all three required elements: magnitude, target year and baseline/reference point. | AI-assisted evidence retrieval; not yet personally verified by the researcher.
A134: Thai Main Sample | B134: GULF | C134: 2023 | D134: Energy | E134: Q3 | F134: SBTi-Validated Target | G134: 0 | H134: AI preliminary 0/uncertain — researcher verification required | I134: No explicit SBTi validation statement found in the selected reports. | J134: GULF Sustainability Report 2023.pdf | L134: https://sustainability.gulf.co.th/en/document/sustainability-reports | M134: No | O134: =IF(N134<>"",N134,G134) -> 0 | P134: No official SBTi validation applicable to the observation year was evidenced; alignment, commitment, submission or later validation does not qualify. | AI-assisted evidence retrieval; not yet personally verified by the researcher.
A135: Thai Main Sample | B135: GULF | C135: 2023 | D135: Energy | E135: Q4 | F135: Quantitative Scope 1 and Scope 2 Disclosure | G135: 1 | H135: AI evidence found — researcher verification required | I135: 24.68 Climate strategy Greenhouse gas (GHG) emissions Net Zero by Total GHG emissions Tonnes 3,944,773 5,109,713 8,791,140 14,624,745 2050 tCO2e / Total emissions intensity 0.401 0.406 0.389 0.469 MWh Direct emissions (scope 1) Tonnes 3,931,649 5,094,990 6,651,222 11,245,262 tCO2e / Reduce by Total scope 1 intensity 0.400 0.405 0.386 0.360 25% by 2030 MWh Indirect emissions (scope 2)11 Tonnes 10,762 10,782 53,794 23,547 tCO2e / Total scope 2 intensity 0.001 0.001 0.003 0.001 MWh Other indirect emissions Tonnes 2,363 3,941 2,758 3,355,936 (scope 3)12 tCO2e / Total scope 3 intensity 0.000 0.000 0.000 0.108 MWh SF6 emissions Tonnes 0.013 1.178 0.007 30,36213 Product stewardship Electricity transmission and distribution losses14 Tran | J135: GULF ESG 2023.pdf | K135: p. 12 | L135: https://sustainability.gulf.co.th/en/document/sustainability-reports | M135: No | O135: =IF(N135<>"",N135,G135) -> 1 | P135: Quantitative Scope 1 and Scope 2 emissions are disclosed with numerical data. | AI-assisted evidence retrieval; not yet personally verified by the researcher.
A136: Thai Main Sample | B136: GULF | C136: 2023 | D136: Energy | E136: Q5 | F136: Quantitative Scope 3 Disclosure | G136: 1 | H136: AI evidence found — researcher verification required | I136: .405 0.386 0.360 25% by 2030 MWh Indirect emissions (scope 2)11 Tonnes 10,762 10,782 53,794 23,547 tCO2e / Total scope 2 intensity 0.001 0.001 0.003 0.001 MWh Other indirect emissions Tonnes 2,363 3,941 2,758 3,355,936 (scope 3)12 tCO2e / Total scope 3 intensity 0.000 0.000 0.000 0.108 MWh SF6 emissions Tonnes 0.013 1.178 0.007 30,36213 Product stewardship Electricity transmission and distribution losses14 Transmission losses % 0.49 0.53 0.51 0.66 Distribution losses % N/A N/A N/A N/A Electricity transmission and distribution reliability SAIDI (transmission network) Hours 8 6 5 3 Gas leakage rate15 Transportation leakages % 0.0019 0.0087 0.0071 Distribution leakages % N/A N/A N/A N/A Storage leakages % N/A N/A N/A N/A Efficiency o | J136: GULF ESG 2023.pdf | K136: p. 12 | L136: https://sustainability.gulf.co.th/en/document/sustainability-reports | M136: No | O136: =IF(N136<>"",N136,G136) -> 1 | P136: Quantitative Scope 3 emissions (including financed emissions where relevant) are disclosed. | AI-assisted evidence retrieval; not yet personally verified by the researcher.
A137: Thai Main Sample | B137: GULF | C137: 2023 | D137: Energy | E137: Q6 | F137: Comparable Multi-Year Emissions Data | G137: 0 | H137: AI conservative 0 — evidence snippet did not satisfy all strict rule elements; researcher recheck recommended | I137: 24.68 Climate strategy Greenhouse gas (GHG) emissions Net Zero by Total GHG emissions Tonnes 3,944,773 5,109,713 8,791,140 14,624,745 2050 tCO2e / Total emissions intensity 0.401 0.406 0.389 0.469 MWh Direct emissions (scope 1) Tonnes 3,931,649 5,094,990 6,651,222 11,245,262 tCO2e / Reduce by Total scope 1 intensity 0.400 0.405 0.386 0.360 25% by 2030 MWh Indirect emissions (scope 2)11 Tonnes 10,762 10,782 53,794 23,547 tCO2e / Total scope 2 intensity 0.001 0.001 0.003 0.001 MWh Other indirect emissions Tonnes 2,363 3,941 2,758 3,355,936 (scope 3)12 tCO2e / Total scope 3 intensity 0.000 0.000 0.000 0.108 MWh SF6 emissions Tonnes 0.013 1.178 0.007 30,36213 Product stewardship Electricity transmission and distribution losses14 Tran | J137: GULF ESG 2023.pdf | K137: p. 12 | L137: https://sustainability.gulf.co.th/en/document/sustainability-reports | M137: No | O137: =IF(N137<>"",N137,G137) -> 0 | P137: Automated retrieval found a potentially relevant page, but the captured evidence did not contain all strict coding elements together. Conservatively coded 0 pending researcher verification.
A138: Thai Main Sample | B138: GULF | C138: 2023 | D138: Energy | E138: Q7 | F138: Transition Implementation & Resource Allocation | G138: 1 | H138: AI evidence found — researcher verification required | I138: acity MW 1,730.6 3,171.9 4,624.6 5,967.8 ▪ Conventional capacity MW 1,586.2 2,911.2 4,236.2 5,561.2 ▪ Natural gas-fired MW 1,586.2 2,911.2 4,236.2 5,561.2 > 40% ▪ Renewable capacity MW 144.4 260.7 388.4 406.6 by 20352 ▪ Solar MW 119.4 231.7 235.4 253.6 > 25003 ▪ Wind MW - 4 128 128 > 1,2003 ▪ Biomass MW 25 25 25 25 ▪ Other4 MW - - - - > 1,5003 Total electricity generation MWh 10,291,828 13,162,988 17,844,187 31,466,827 ▪ Conventional sources MWh 9,973,215 12,827,034 17,496,609 30,966,724 ▪ Gas-fired generation MWh 9,973,215 12,827,034 17,496,609 30,966,724 ▪ Renewable sources MWh 318,613 335,954 347,578 500,103 ▪ Solar MWh 180,077 161,898 175,250 182,231 ▪ Wind MWh - - 7,399 153,595 ▪ Biomass MWh 138,536 174,056 172,328 172,312 ▪ | J138: GULF ESG 2023.pdf | K138: p. 1 | L138: https://sustainability.gulf.co.th/en/document/sustainability-reports | M138: No | O138: =IF(N138<>"",N138,G138) -> 1 | P138: Concrete transition action is linked to a measurable financial or operational resource allocation. | AI-assisted evidence retrieval; not yet personally verified by the researcher.
A139: Thai Main Sample | B139: GULF | C139: 2023 | D139: Energy | E139: Q8 | F139: Board-Level Climate Oversight | G139: 0 | H139: AI preliminary 0/uncertain — researcher verification required | I139: Governance Dimension Topic Unit 2020 2021 2022 2023 Target Corporate governance Board of Directors (1-tier system) Total People 11 10 12 12 ▪ Independent directors People 6 5 7 7 ▪ Executive directors People 4 4 4 4 ▪ Non-executive directors People 1 1 1 1 ▪ Proportion of females % 36 40 33 33 ≥ 33 Board meeting attendance1 % 91.4 97.7 98.8 94.9 ≥ 752 Business ethics Written / digital acknowledgement of Codes of Conduct ▪ Employees % 100 100 100 100 100 ▪ Suppliers3 % 100 100 100 100 100 ▪ Subsidiaries % 100 100 100 100 100 ▪ Joint ventures4 % 100 100 100 100 100 Anti-corruption and bribery Op | J139: GULF ESG 2023.pdf | K139: p. 2 | L139: https://sustainability.gulf.co.th/en/document/sustainability-reports | M139: No | O139: =IF(N139<>"",N139,G139) -> 0 | P139: Governance is described but explicit board-level climate/sustainability oversight was not sufficiently evidenced. | AI-assisted evidence retrieval; not yet personally verified by the researcher.
A140: Thai Main Sample | B140: GULF | C140: 2023 | D140: Energy | E140: Q9 | F140: Measurable Progress Against Targets | G140: 0 | H140: AI preliminary 0/uncertain — researcher verification required | I140: Social Dimension Topic Unit 2020 2021 2022 2023 Target Labor practice indicators Workforce breakdown by number of employees Total People 886 919 1,074 1,168 ▪ Males People 611 633 741 779 ▪ Proportion of males % 69.0 68.9 69.0 66.7 ▪ Females People 275 286 333 389 ▪ Proportion of females % 31.0 31.1 31.0 33.3 ≥ 30 Workforce breakdown by type of contract Permanent People 825 872 1,004 1,130 Contract People 61 47 70 38 Workforce breakdown by function Energy business People 68 81 134 177 Power projects People 478 477 534 548 Other businesses and People 22 25 40 42 | J140: GULF ESG 2023.pdf | K140: p. 5 | L140: https://sustainability.gulf.co.th/en/document/sustainability-reports | M140: No | O140: =IF(N140<>"",N140,G140) -> 0 | P140: Quantitative emissions are present but measurable progress against a target/baseline/pathway was not sufficiently evidenced. | AI-assisted evidence retrieval; not yet personally verified by the researcher.
A141: Thai Main Sample | B141: GULF | C141: 2023 | D141: Energy | E141: Q10 | F141: Independent External Assurance | G141: 0 | H141: AI conservative 0 — evidence snippet did not satisfy all strict rule elements; researcher recheck recommended | I141: Independent Assurance Statement Introduction and Engagement Gulf Energy Development Public Company Limited (hereafter ‘GULF’) commissioned TÜV NORD (Thailand) Ltd. (hereafter ‘TUVN’) for Sustainability Assurance Engagement. TUV NORD provide independent assurance on GULF’s sustainability information, its Safety, Health and Environmental (SH&E) data (hereinafter ‘the Report’), for the applied reporting period for the calendar year 2023. This assurance engagement was conducted against the Global Reporting Initiative Standards a l | J141: GULF assurance 2023.pdf | K141: p. 1 | L141: https://sustainability.gulf.co.th/en/document/sustainability-reports | M141: No | O141: =IF(N141<>"",N141,G141) -> 0 | P141: Automated retrieval found a potentially relevant page, but the captured evidence did not contain all strict coding elements together. Conservatively coded 0 pending researcher verification.
A142: Thai Main Sample | B142: GULF | C142: 2024 | D142: Energy | E142: Q1 | F142: Time-Bound Net-Zero Target | G142: 1 | H142: 2024 pilot evidence pass: Verified | I142: GULF reports a Net Zero target for 2050. | J142: GULF Quantitative ESG Data 2024 | K142: Climate strategy | L142: https://sustainability.gulf.co.th/storage/document/sustainability-reports/2024/quantitative-esg-data-2024-en.pdf | M142: No | O142: =IF(N142<>"",N142,G142) -> 1 | P142: Explicit net-zero target and year. | Imported from the earlier 2024 evidence workbook; researcher personal verification is still required before treating this as final dissertation coding.
A143: Thai Main Sample | B143: GULF | C143: 2024 | D143: Energy | E143: Q2 | F143: Measurable Interim Emissions-Reduction Target | G143: 1 | H143: 2024 pilot evidence pass: Verified | I143: GULF targets a 25% reduction in Scope 1 emissions intensity by 2030 from the 2019 baseline. | J143: GULF Quantitative ESG Data 2024 | K143: Climate strategy | L143: https://sustainability.gulf.co.th/storage/document/sustainability-reports/2024/quantitative-esg-data-2024-en.pdf | M143: No | O143: =IF(N143<>"",N143,G143) -> 1 | P143: Quantitative target, target year and baseline. | Imported from the earlier 2024 evidence workbook; researcher personal verification is still required before treating this as final dissertation coding.
A144: Thai Main Sample | B144: GULF | C144: 2024 | D144: Energy | E144: Q3 | F144: SBTi-Validated Target | G144: 0 | H144: 2024 pilot evidence pass: Conservative 0 / dashboard recheck | I144: No 2024 entity-level SBTi validation was confirmed for GULF. | J144: SBTi Target Dashboard | K144: Search GULF | L144: https://sciencebasedtargets.org/target-dashboard | M144: No | O144: =IF(N144<>"",N144,G144) -> 0 | P144: Conservative strict rule. | Imported from the earlier 2024 evidence workbook; researcher personal verification is still required before treating this as final dissertation coding.
A145: Thai Main Sample | B145: GULF | C145: 2024 | D145: Energy | E145: Q4 | F145: Quantitative Scope 1 and Scope 2 Disclosure | G145: 1 | H145: 2024 pilot evidence pass: Verified | I145: GULF reports 2024 Scope 1 and Scope 2 emissions quantitatively. | J145: GULF Quantitative ESG Data 2024 | K145: Environmental data table | L145: https://sustainability.gulf.co.th/storage/document/sustainability-reports/2024/quantitative-esg-data-2024-en.pdf | M145: No | O145: =IF(N145<>"",N145,G145) -> 1 | P145: Quantitative Scope 1 and 2 values. | Imported from the earlier 2024 evidence workbook; researcher personal verification is still required before treating this as final dissertation coding.
A146: Thai Main Sample | B146: GULF | C146: 2024 | D146: Energy | E146: Q5 | F146: Quantitative Scope 3 Disclosure | G146: 1 | H146: 2024 pilot evidence pass: Verified | I146: GULF reports quantitative Scope 3 emissions; 2024 value is included in its ESG data table. | J146: GULF Quantitative ESG Data 2024 | K146: Environmental data table | L146: https://sustainability.gulf.co.th/storage/document/sustainability-reports/2024/quantitative-esg-data-2024-en.pdf | M146: No | O146: =IF(N146<>"",N146,G146) -> 1 | P146: Quantitative Scope 3 disclosed. | Imported from the earlier 2024 evidence workbook; researcher personal verification is still required before treating this as final dissertation coding.
... A204: Thai Main Sample | B204: SCBX | C204: 2022 | D204: Financial Services | E204: Q3 | F204: SBTi-Validated Target | G204: 0 | H204: AI preliminary 0/uncertain — researcher verification required | I204: long terms. The Group. identification is the first step of Materiality Assessment under the Global Reporting Initiative (GRI) Standards, that involves internal and external stakeholders The Group materiality topics are approved by the Board of Directors and reviewed on a yearly basis through the SCBX 1 2 including customers, investors, regulators, Management Committee. and business partners. In 2022, SCBX identified a total of 123 materiality sustainability issues, which were Analyse the alignment with SCBX Assess and prioritise ESG issues with categorized into 31 topics. Of all topics, 12 enterprise risk management respect to importance to SCBX and we re c o n s i d e re d s i g n i fi c a nt a n d framework and SCBX strategic s | J204: SCBX sus report 2022.pdf | K204: p. 17 | L204: https://www.scbx.com/th/sustainability/report-and-disclosures/ | M204: No | O204: =IF(N204<>"",N204,G204) -> 0 | P204: No official SBTi validation applicable to the observation year was evidenced; alignment, commitment, submission or later validation does not qualify. | AI-assisted evidence retrieval; not yet personally verified by the researcher.
A205: Thai Main Sample | B205: SCBX | C205: 2022 | D205: Financial Services | E205: Q4 | F205: Quantitative Scope 1 and Scope 2 Disclosure | G205: 0 | H205: AI preliminary 0/uncertain — researcher verification required | I205: No qualifying evidence found in selected report(s). | J205: SCBX sus report 2022.pdf | L205: https://www.scbx.com/th/sustainability/report-and-disclosures/ | M205: No | O205: =IF(N205<>"",N205,G205) -> 0 | P205: No qualifying evidence found under the strict coding rule. | AI-assisted evidence retrieval; not yet personally verified by the researcher.
A206: Thai Main Sample | B206: SCBX | C206: 2022 | D206: Financial Services | E206: Q5 | F206: Quantitative Scope 3 Disclosure | G206: 0 | H206: AI preliminary 0/uncertain — researcher verification required | I206: No qualifying evidence found in selected report(s). | J206: SCBX sus report 2022.pdf | L206: https://www.scbx.com/th/sustainability/report-and-disclosures/ | M206: No | O206: =IF(N206<>"",N206,G206) -> 0 | P206: No qualifying evidence found under the strict coding rule. | AI-assisted evidence retrieval; not yet personally verified by the researcher.
A207: Thai Main Sample | B207: SCBX | C207: 2022 | D207: Financial Services | E207: Q6 | F207: Comparable Multi-Year Emissions Data | G207: 0 | H207: AI preliminary 0/uncertain — researcher verification required | I207: eryone can of this success.” do it and it’s also fun.” Credit risk personnel Credit risk personnel Market risk personnel Operational risk personnel Human Capital Return on Investment Performance Indicator 2019 2020 2021 2022 Human capital return on investment 3.87 3.84 4.25 3.71 Total cost of SCBX Group Employee Training Hours employee development 171 Performance Indicator 2019 2020 2021 2022 2022 Target million THB Average training hour (hour/person) 68 49 44 53 40 LESS FOR BETTER | SCBX Sustainability Report 2022 | J207: SCBX sus report 2022.pdf | K207: p. 35 | L207: https://www.scbx.com/th/sustainability/report-and-disclosures/ | M207: No | O207: =IF(N207<>"",N207,G207) -> 0 | P207: A multi-year emissions series was not sufficiently evidenced on the selected disclosure. | AI-assisted evidence retrieval; not yet personally verified by the researcher.
A208: Thai Main Sample | B208: SCBX | C208: 2022 | D208: Financial Services | E208: Q7 | F208: Transition Implementation & Resource Allocation | G208: 0 | H208: AI preliminary 0/uncertain — researcher verification required | I208: r data. I am proud to be part coding is easy; everyone can of this success.” do it and it’s also fun.” Credit risk personnel Credit risk personnel Market risk personnel Operational risk personnel Human Capital Return on Investment Performance Indicator 2019 2020 2021 2022 Human capital return on investment 3.87 3.84 4.25 3.71 Total cost of SCBX Group Employee Training Hours employee development 171 Performance Indicator 2019 2020 2021 2022 2022 Target million THB Average training hour (hour/person) 68 49 44 53 40 LESS FOR BETTER | SCBX Sustainability Report 2022 | J208: SCBX sus report 2022.pdf | K208: p. 35 | L208: https://www.scbx.com/th/sustainability/report-and-disclosures/ | M208: No | O208: =IF(N208<>"",N208,G208) -> 0 | P208: Transition actions are described, but a measurable resource allocation was not sufficiently evidenced under the strict rule. | AI-assisted evidence retrieval; not yet personally verified by the researcher.
A209: Thai Main Sample | B209: SCBX | C209: 2022 | D209: Financial Services | E209: Q8 | F209: Board-Level Climate Oversight | G209: 1 | H209: AI evidence found — researcher verification required | I209: SCBX OVERVIEW PLANTING DIGITAL SEEDS ENRICHING LIVES GROWING ECONOMIC RESILIENCE REACHING CLIMATE NEUTRALITY FOUNDATION FACTBOOK 15 Message from the Chairman SCBX at a Glance Sustainability at SCBX of the Board of Directors and Chief Executive Officer SUSTAINABILITY GOVERNANCE SCBX To ensure adherence to the SCBX Group Sustainability Policy and framework with systematic deployment, the sustainability BOARD OF DIRECTORS governance structure at the Group level has been Oversees overall Group sustainability policy and framework, ensures effective governance, specified and tasked with roles and responsibilities and regularly monitors performance from the Board of Directors to subsidiaries in order to embed sustainabilit | J209: SCBX sus report 2022.pdf | K209: p. 16 | L209: https://www.scbx.com/th/sustainability/report-and-disclosures/ | M209: No | O209: =IF(N209<>"",N209,G209) -> 1 | P209: Board or board-level committee has explicit oversight/responsibility for climate or sustainability matters. | AI-assisted evidence retrieval; not yet personally verified by the researcher.
...

Sheet Summary
A1: Type | B1: Company | C1: Year | D1: Verified Criteria | E1: Final Raw /10 | F1: NZTDCI /100 | G1: Assistant Scores Completed | H1: Assistant Proposed Raw | I1: Assistant Proposed NZTDCI | J1: Ready for Analysis?
A2: Thai Main Sample | B2: PTT | C2: 2022 | D2: =COUNTIFS(Coding_800!$B$2:$B$801,B2,Coding_800!$C$2:$C$801,C2,Coding_800!$M$2:$M$801,"Yes") -> 0 | E2: =SUMIFS(Coding_800!$O$2:$O$801,Coding_800!$B$2:$B$801,B2,Coding_800!$C$2:$C$801,C2) -> 2 | F2: =E2*10 -> 20 | G2: =COUNTIFS(Coding_800!$B$2:$B$801,B2,Coding_800!$C$2:$C$801,C2,Coding_800!$G$2:$G$801,">=0") -> 10 | H2: =SUMIFS(Coding_800!$G$2:$G$801,Coding_800!$B$2:$B$801,B2,Coding_800!$C$2:$C$801,C2) -> 2 | I2: =H2*10 -> 20 | J2: =IF(D2=10,"Yes - researcher verified","Provisional - researcher check pending") -> Provisional - researcher check pending
A3: Thai Main Sample | B3: PTT | C3: 2023 | D3: =COUNTIFS(Coding_800!$B$2:$B$801,B3,Coding_800!$C$2:$C$801,C3,Coding_800!$M$2:$M$801,"Yes") -> 0 | E3: =SUMIFS(Coding_800!$O$2:$O$801,Coding_800!$B$2:$B$801,B3,Coding_800!$C$2:$C$801,C3) -> 4 | F3: =E3*10 -> 40 | G3: =COUNTIFS(Coding_800!$B$2:$B$801,B3,Coding_800!$C$2:$C$801,C3,Coding_800!$G$2:$G$801,">=0") -> 10 | H3: =SUMIFS(Coding_800!$G$2:$G$801,Coding_800!$B$2:$B$801,B3,Coding_800!$C$2:$C$801,C3) -> 4 | I3: =H3*10 -> 40 | J3: =IF(D3=10,"Yes - researcher verified","Provisional - researcher check pending") -> Provisional - researcher check pending
A4: Thai Main Sample | B4: PTT | C4: 2024 | D4: =COUNTIFS(Coding_800!$B$2:$B$801,B4,Coding_800!$C$2:$C$801,C4,Coding_800!$M$2:$M$801,"Yes") -> 0 | E4: =SUMIFS(Coding_800!$O$2:$O$801,Coding_800!$B$2:$B$801,B4,Coding_800!$C$2:$C$801,C4) -> 8 | F4: =E4*10 -> 80 | G4: =COUNTIFS(Coding_800!$B$2:$B$801,B4,Coding_800!$C$2:$C$801,C4,Coding_800!$G$2:$G$801,">=0") -> 10 | H4: =SUMIFS(Coding_800!$G$2:$G$801,Coding_800!$B$2:$B$801,B4,Coding_800!$C$2:$C$801,C4) -> 8 | I4: =H4*10 -> 80 | J4: =IF(D4=10,"Yes - researcher verified","Provisional - researcher check pending") -> Provisional - researcher check pending
A5: Thai Main Sample | B5: PTT | C5: 2025 | D5: =COUNTIFS(Coding_800!$B$2:$B$801,B5,Coding_800!$C$2:$C$801,C5,Coding_800!$M$2:$M$801,"Yes") -> 0 | E5: =SUMIFS(Coding_800!$O$2:$O$801,Coding_800!$B$2:$B$801,B5,Coding_800!$C$2:$C$801,C5) -> 5 | F5: =E5*10 -> 50 | G5: =COUNTIFS(Coding_800!$B$2:$B$801,B5,Coding_800!$C$2:$C$801,C5,Coding_800!$G$2:$G$801,">=0") -> 10 | H5: =SUMIFS(Coding_800!$G$2:$G$801,Coding_800!$B$2:$B$801,B5,Coding_800!$C$2:$C$801,C5) -> 5 | I5: =H5*10 -> 50 | J5: =IF(D5=10,"Yes - researcher verified","Provisional - researcher check pending") -> Provisional - researcher check pending
A6: Thai Main Sample | B6: PTTEP | C6: 2022 | D6: =COUNTIFS(Coding_800!$B$2:$B$801,B6,Coding_800!$C$2:$C$801,C6,Coding_800!$M$2:$M$801,"Yes") -> 0 | E6: =SUMIFS(Coding_800!$O$2:$O$801,Coding_800!$B$2:$B$801,B6,Coding_800!$C$2:$C$801,C6) -> 2 | F6: =E6*10 -> 20 | G6: =COUNTIFS(Coding_800!$B$2:$B$801,B6,Coding_800!$C$2:$C$801,C6,Coding_800!$G$2:$G$801,">=0") -> 10 | H6: =SUMIFS(Coding_800!$G$2:$G$801,Coding_800!$B$2:$B$801,B6,Coding_800!$C$2:$C$801,C6) -> 2 | I6: =H6*10 -> 20 | J6: =IF(D6=10,"Yes - researcher verified","Provisional - researcher check pending") -> Provisional - researcher check pending
A7: Thai Main Sample | B7: PTTEP | C7: 2023 | D7: =COUNTIFS(Coding_800!$B$2:$B$801,B7,Coding_800!$C$2:$C$801,C7,Coding_800!$M$2:$M$801,"Yes") -> 0 | E7: =SUMIFS(Coding_800!$O$2:$O$801,Coding_800!$B$2:$B$801,B7,Coding_800!$C$2:$C$801,C7) -> 2 | F7: =E7*10 -> 20 | G7: =COUNTIFS(Coding_800!$B$2:$B$801,B7,Coding_800!$C$2:$C$801,C7,Coding_800!$G$2:$G$801,">=0") -> 10 | H7: =SUMIFS(Coding_800!$G$2:$G$801,Coding_800!$B$2:$B$801,B7,Coding_800!$C$2:$C$801,C7) -> 2 | I7: =H7*10 -> 20 | J7: =IF(D7=10,"Yes - researcher verified","Provisional - researcher check pending") -> Provisional - researcher check pending
A8: Thai Main Sample | B8: PTTEP | C8: 2024 | D8: =COUNTIFS(Coding_800!$B$2:$B$801,B8,Coding_800!$C$2:$C$801,C8,Coding_800!$M$2:$M$801,"Yes") -> 0 | E8: =SUMIFS(Coding_800!$O$2:$O$801,Coding_800!$B$2:$B$801,B8,Coding_800!$C$2:$C$801,C8) -> 9 | F8: =E8*10 -> 90 | G8: =COUNTIFS(Coding_800!$B$2:$B$801,B8,Coding_800!$C$2:$C$801,C8,Coding_800!$G$2:$G$801,">=0") -> 10 | H8: =SUMIFS(Coding_800!$G$2:$G$801,Coding_800!$B$2:$B$801,B8,Coding_800!$C$2:$C$801,C8) -> 9 | I8: =H8*10 -> 90 | J8: =IF(D8=10,"Yes - researcher verified","Provisional - researcher check pending") -> Provisional - researcher check pending
A9: Thai Main Sample | B9: PTTEP | C9: 2025 | D9: =COUNTIFS(Coding_800!$B$2:$B$801,B9,Coding_800!$C$2:$C$801,C9,Coding_800!$M$2:$M$801,"Yes") -> 0 | E9: =SUMIFS(Coding_800!$O$2:$O$801,Coding_800!$B$2:$B$801,B9,Coding_800!$C$2:$C$801,C9) -> 2 | F9: =E9*10 -> 20 | G9: =COUNTIFS(Coding_800!$B$2:$B$801,B9,Coding_800!$C$2:$C$801,C9,Coding_800!$G$2:$G$801,">=0") -> 10 | H9: =SUMIFS(Coding_800!$G$2:$G$801,Coding_800!$B$2:$B$801,B9,Coding_800!$C$2:$C$801,C9) -> 2 | I9: =H9*10 -> 20 | J9: =IF(D9=10,"Yes - researcher verified","Provisional - researcher check pending") -> Provisional - researcher check pending
A10: Thai Main Sample | B10: GPSC | C10: 2022 | D10: =COUNTIFS(Coding_800!$B$2:$B$801,B10,Coding_800!$C$2:$C$801,C10,Coding_800!$M$2:$M$801,"Yes") -> 0 | E10: =SUMIFS(Coding_800!$O$2:$O$801,Coding_800!$B$2:$B$801,B10,Coding_800!$C$2:$C$801,C10) -> 2 | F10: =E10*10 -> 20 | G10: =COUNTIFS(Coding_800!$B$2:$B$801,B10,Coding_800!$C$2:$C$801,C10,Coding_800!$G$2:$G$801,">=0") -> 10 | H10: =SUMIFS(Coding_800!$G$2:$G$801,Coding_800!$B$2:$B$801,B10,Coding_800!$C$2:$C$801,C10) -> 2 | I10: =H10*10 -> 20 | J10: =IF(D10=10,"Yes - researcher verified","Provisional - researcher check pending") -> Provisional - researcher check pending
A11: Thai Main Sample | B11: GPSC | C11: 2023 | D11: =COUNTIFS(Coding_800!$B$2:$B$801,B11,Coding_800!$C$2:$C$801,C11,Coding_800!$M$2:$M$801,"Yes") -> 0 | E11: =SUMIFS(Coding_800!$O$2:$O$801,Coding_800!$B$2:$B$801,B11,Coding_800!$C$2:$C$801,C11) -> 4 | F11: =E11*10 -> 40 | G11: =COUNTIFS(Coding_800!$B$2:$B$801,B11,Coding_800!$C$2:$C$801,C11,Coding_800!$G$2:$G$801,">=0") -> 10 | H11: =SUMIFS(Coding_800!$G$2:$G$801,Coding_800!$B$2:$B$801,B11,Coding_800!$C$2:$C$801,C11) -> 4 | I11: =H11*10 -> 40 | J11: =IF(D11=10,"Yes - researcher verified","Provisional - researcher check pending") -> Provisional - researcher check pending
A12: Thai Main Sample | B12: GPSC | C12: 2024 | D12: =COUNTIFS(Coding_800!$B$2:$B$801,B12,Coding_800!$C$2:$C$801,C12,Coding_800!$M$2:$M$801,"Yes") -> 0 | E12: =SUMIFS(Coding_800!$O$2:$O$801,Coding_800!$B$2:$B$801,B12,Coding_800!$C$2:$C$801,C12) -> 8 | F12: =E12*10 -> 80 | G12: =COUNTIFS(Coding_800!$B$2:$B$801,B12,Coding_800!$C$2:$C$801,C12,Coding_800!$G$2:$G$801,">=0") -> 10 | H12: =SUMIFS(Coding_800!$G$2:$G$801,Coding_800!$B$2:$B$801,B12,Coding_800!$C$2:$C$801,C12) -> 8 | I12: =H12*10 -> 80 | J12: =IF(D12=10,"Yes - researcher verified","Provisional - researcher check pending") -> Provisional - researcher check pending
A13: Thai Main Sample | B13: GPSC | C13: 2025 | D13: =COUNTIFS(Coding_800!$B$2:$B$801,B13,Coding_800!$C$2:$C$801,C13,Coding_800!$M$2:$M$801,"Yes") -> 0 | E13: =SUMIFS(Coding_800!$O$2:$O$801,Coding_800!$B$2:$B$801,B13,Coding_800!$C$2:$C$801,C13) -> 3 | F13: =E13*10 -> 30 | G13: =COUNTIFS(Coding_800!$B$2:$B$801,B13,Coding_800!$C$2:$C$801,C13,Coding_800!$G$2:$G$801,">=0") -> 10 | H13: =SUMIFS(Coding_800!$G$2:$G$801,Coding_800!$B$2:$B$801,B13,Coding_800!$C$2:$C$801,C13) -> 3 | I13: =H13*10 -> 30 | J13: =IF(D13=10,"Yes - researcher verified","Provisional - researcher check pending") -> Provisional - researcher check pending
... A81: International Benchmark | B81: HOLCIM | C81: 2025 | D81: =COUNTIFS(Coding_800!$B$2:$B$801,B81,Coding_800!$C$2:$C$801,C81,Coding_800!$M$2:$M$801,"Yes") -> 0 | E81: =SUMIFS(Coding_800!$O$2:$O$801,Coding_800!$B$2:$B$801,B81,Coding_800!$C$2:$C$801,C81) -> 6 | F81: =E81*10 -> 60 | G81: =COUNTIFS(Coding_800!$B$2:$B$801,B81,Coding_800!$C$2:$C$801,C81,Coding_800!$G$2:$G$801,">=0") -> 10 | H81: =SUMIFS(Coding_800!$G$2:$G$801,Coding_800!$B$2:$B$801,B81,Coding_800!$C$2:$C$801,C81) -> 6 | I81: =H81*10 -> 60 | J81: =IF(D81=10,"Yes - researcher verified","Provisional - researcher check pending") -> Provisional - researcher check pending

Sheet Financial_Data_Thai
A1: Company | B1: Year | C1: Sector | D1: Net Income | E1: Total Assets | F1: Prior-Year Assets | G1: Average Assets | H1: Total Equity | I1: Prior-Year Equity | J1: Average Equity | K1: Total Liabilities | L1: Revenue | M1: ROA % | N1: ROE % | O1: ln(Assets) | P1: Leverage %
A2: PTT | B2: 2022 | C2: Energy | D2: 91174.86 | E2: 3415632.3 | F2: 3078018.8 | G2: 3246825.6 | H2: 1052590.9 | I2: 1006696.2 | J2: 1029643.6 | K2: 1881939.5 | L2: 3391622.9 | M2: 0.028081 | N2: 0.08855 | O2: 15.043873 | P2: 0.550978
A3: PTT | B3: 2023 | C3: Energy | D3: 112023.88 | E3: 3460461.9 | F3: 3415632.3 | G3: 3438047.1 | H3: 1121197.9 | I3: 1052590.9 | J3: 1086894.4 | K3: 1835486.5 | L3: 3185256.1 | M3: 0.032584 | N3: 0.103068 | O3: 15.056913 | P3: 0.530417
A4: PTT | B4: 2024 | C4: Energy | D4: 90072.08 | E4: 3438784.3 | F4: 3460461.9 | G4: 3449623.1 | H4: 1149652.2 | I4: 1121197.9 | J4: 1135425 | K4: 1781907.2 | L4: 3138378 | M4: 0.026111 | N4: 0.079329 | O4: 15.050629 | P4: 0.518179
A5: PTT | B5: 2025 | C5: Energy | D5: 90166.37 | E5: 3269660 | F5: 3438784.3 | G5: 3354222.1 | H5: 1127422.1 | I5: 1149652.2 | J5: 1138537.1 | K5: 1617176.4 | L5: 2707981.7 | M5: 0.026881 | N5: 0.079195 | O5: 15.000197 | P5: 0.494601
A6: PTTEP | B6: 2022 | C6: Energy | D6: 70901.34 | E6: 869864.32 | F6: 783535.67 | G6: 826700 | H6: 467120.61 | I6: 415349.75 | J6: 441235.18 | K6: 402743.72 | L6: 339901.86 | M6: 0.085764 | N6: 0.160688 | O6: 13.676093 | P6: 0.462996
A7: PTTEP | B7: 2023 | C7: Energy | D7: 76706.39 | E7: 902820.93 | F7: 869864.32 | G7: 886342.63 | H7: 499326.5 | I7: 467120.61 | J7: 483223.56 | K7: 403378.12 | L7: 313590.65 | M7: 0.086543 | N7: 0.158739 | O7: 13.71328 | P7: 0.446797
A8: PTTEP | B8: 2024 | C8: Energy | D8: 78824.24 | E8: 965300.75 | F8: 902820.93 | G8: 934060.84 | H8: 535594.82 | I8: 499326.5 | J8: 517460.66 | K8: 429425.05 | L8: 326830.16 | M8: 0.084389 | N8: 0.152329 | O8: 13.780195 | P8: 0.444861
A9: PTTEP | B9: 2025 | C9: Energy | D9: 60273.15 | E9: 933936.67 | F9: 965300.75 | G9: 949618.71 | H9: 519305.02 | I9: 535594.82 | J9: 527449.92 | K9: 414368.93 | L9: 292632.65 | M9: 0.063471 | N9: 0.114273 | O9: 13.747164 | P9: 0.44368
A10: GPSC | B10: 2022 | C10: Energy | D10: 891.45 | E10: 288810.09 | F10: 270379.12 | G10: 279594.61 | H10: 104729.96 | I10: 108334.28 | J10: 106532.12 | K10: 173709.87 | L10: 126416.06 | M10: 0.003188 | N10: 0.008368 | O10: 12.573525 | P10: 0.601467
A11: GPSC | B11: 2023 | C11: Energy | D11: 3694.22 | E11: 285889.5 | F11: 288810.09 | G11: 287349.8 | H11: 106195.04 | I11: 104729.96 | J11: 105462.5 | K11: 167150.01 | L11: 93093.57 | M11: 0.012856 | N11: 0.035029 | O11: 12.563361 | P11: 0.584666
A12: GPSC | B12: 2024 | C12: Energy | D12: 4062.38 | E12: 288136.05 | F12: 285889.5 | G12: 287012.78 | H12: 107557.6 | I12: 106195.04 | J12: 106876.32 | K12: 168994.38 | L12: 92798.76 | M12: 0.014154 | N12: 0.03801 | O12: 12.571188 | P12: 0.586509
A13: GPSC | B13: 2025 | C13: Energy | D13: 6399 | E13: 264259.09 | F13: 288136.05 | G13: 276197.57 | H13: 104406.32 | I13: 107557.6 | J13: 105981.96 | K13: 147823.45 | L13: 87493.29 | M13: 0.023168 | N13: 0.060378 | O13: 12.484685 | P13: 0.559388
... A61: BDMS | B61: 2025 | C61: Healthcare | D61: 15848.22 | E61: 157961.09 | F61: 151514.07 | G61: 154737.58 | H61: 105894.28 | I61: 100036.58 | J61: 102965.43 | K61: 47952.32 | L61: 113385.87 | M61: 0.10242 | N61: 0.153918 | O61: 11.970104 | P61: 0.30357

Sheet Benchmark_Comparison
A1: Benchmark | B1: Country | C1: Sector | D1: Why Selected | E1: 2022 NZTDCI | F1: 2023 NZTDCI | G1: 2024 NZTDCI | H1: 2025 NZTDCI
A2: HSBC | B2: United Kingdom | C2: Banking | D2: Global banking benchmark; relevant to KBANK/SCBX/BBL and financed-emissions disclosure. | E2: =SUMIFS(Summary!$I$2:$I$81,Summary!$B$2:$B$81,$A2,Summary!$C$2:$C$81,2022) -> 60 | F2: =SUMIFS(Summary!$I$2:$I$81,Summary!$B$2:$B$81,$A2,Summary!$C$2:$C$81,2023) -> 60 | G2: =SUMIFS(Summary!$I$2:$I$81,Summary!$B$2:$B$81,$A2,Summary!$C$2:$C$81,2024) -> 80 | H2: =SUMIFS(Summary!$I$2:$I$81,Summary!$B$2:$B$81,$A2,Summary!$C$2:$C$81,2025) -> 70
A3: HEIDELBERG | B3: Germany | C3: Materials | D3: Hard-to-abate materials benchmark; directly comparable to SCC on transition planning. | E3: =SUMIFS(Summary!$I$2:$I$81,Summary!$B$2:$B$81,$A3,Summary!$C$2:$C$81,2022) -> 40 | F3: =SUMIFS(Summary!$I$2:$I$81,Summary!$B$2:$B$81,$A3,Summary!$C$2:$C$81,2023) -> 50 | G3: =SUMIFS(Summary!$I$2:$I$81,Summary!$B$2:$B$81,$A3,Summary!$C$2:$C$81,2024) -> 40 | H3: =SUMIFS(Summary!$I$2:$I$81,Summary!$B$2:$B$81,$A3,Summary!$C$2:$C$81,2025) -> 40
A4: UNILEVER | B4: United Kingdom | C4: Consumer Goods | D4: Consumer/retail benchmark; useful for value-chain and Scope 3 transition disclosure. | E4: =SUMIFS(Summary!$I$2:$I$81,Summary!$B$2:$B$81,$A4,Summary!$C$2:$C$81,2022) -> 50 | F4: =SUMIFS(Summary!$I$2:$I$81,Summary!$B$2:$B$81,$A4,Summary!$C$2:$C$81,2023) -> 70 | G4: =SUMIFS(Summary!$I$2:$I$81,Summary!$B$2:$B$81,$A4,Summary!$C$2:$C$81,2024) -> 80 | H4: =SUMIFS(Summary!$I$2:$I$81,Summary!$B$2:$B$81,$A4,Summary!$C$2:$C$81,2025) -> 40
A5: MAERSK | B5: Denmark | C5: Transport / Logistics | D5: Transport/logistics benchmark; useful for transition-intensive operations and fuel decarbonisation. | E5: =SUMIFS(Summary!$I$2:$I$81,Summary!$B$2:$B$81,$A5,Summary!$C$2:$C$81,2022) -> 70 | F5: =SUMIFS(Summary!$I$2:$I$81,Summary!$B$2:$B$81,$A5,Summary!$C$2:$C$81,2023) -> 70 | G5: =SUMIFS(Summary!$I$2:$I$81,Summary!$B$2:$B$81,$A5,Summary!$C$2:$C$81,2024) -> 70 | H5: =SUMIFS(Summary!$I$2:$I$81,Summary!$B$2:$B$81,$A5,Summary!$C$2:$C$81,2025) -> 60
A6: HOLCIM | B6: Switzerland | C6: Materials / Construction | D6: Major global materials/construction benchmark with extensive net-zero and climate-transition reporting; complements Heidelberg and provides a strong hard-to-abate-sector comparison. | E6: =SUMIFS(Summary!$I$2:$I$81,Summary!$B$2:$B$81,$A6,Summary!$C$2:$C$81,2022) -> 60 | F6: =SUMIFS(Summary!$I$2:$I$81,Summary!$B$2:$B$81,$A6,Summary!$C$2:$C$81,2023) -> 40 | G6: =SUMIFS(Summary!$I$2:$I$81,Summary!$B$2:$B$81,$A6,Summary!$C$2:$C$81,2024) -> 50 | H6: =SUMIFS(Summary!$I$2:$I$81,Summary!$B$2:$B$81,$A6,Summary!$C$2:$C$81,2025) -> 60
